{"@module": "pydefect.input_maker.defect_entry", "@class": "DefectEntry", "@version": "0.10.1", "name": "Al_O1+Va_Mg1.001", "charge": 0, "structure": {"@module": "pymatgen.core.structure", "@class": "IStructure", "charge": 0.0, "lattice": {"matrix": [[16.21153645, 0.0, 0.0], [0.0, 16.21153645, 0.0], [0.0, 0.0, 16.21153645]], "pbc": [true, true, true], "a": 16.21153645, "b": 16.21153645, "c": 16.21153645, "alpha": 90.0, "beta": 90.0, "gamma": 90.0, "volume": 4260.617347507763}, "properties": {}, "sites": [{"species": [{"element": "Mg", "occu": 1}], "abc": [0.125, 0.125, 0.625], "properties": {}, "label": "Mg", "xyz": [2.02644205625, 2.02644205625, 10.13221028125]}, {"species": [{"element": "Mg", "occu": 1}], "abc": [0.125, 0.625, 0.125], "properties": {}, "label": "Mg", "xyz": [2.02644205625, 10.13221028125, 2.02644205625]}, {"species": [{"element": "Mg", "occu": 1}], "abc": [0.125, 0.625, 0.625], "properties": {}, "label": "Mg", "xyz": [2.02644205625, 10.13221028125, 10.13221028125]}, {"species": [{"element": "Mg", "occu": 1}], "abc": [0.625, 0.125, 0.125], "properties": {}, "label": "Mg", "xyz": [10.13221028125, 2.02644205625, 2.02644205625]}, {"species": [{"element": "Mg", "occu": 1}], "abc": [0.625, 0.125, 0.625], "properties": {}, "label": "Mg", "xyz": [10.13221028125, 2.02644205625, 10.13221028125]}, {"species": [{"element": "Mg", "occu": 1}], "abc": [0.625, 0.625, 0.125], "properties": {}, "label": "Mg", "xyz": [10.13221028125, 10.13221028125, 2.02644205625]}, {"species": [{"element": "Mg", "occu": 1}], "abc": [0.625, 0.625, 0.625], "properties": {}, "label": "Mg", "xyz": [10.13221028125, 10.13221028125, 10.13221028125]}, {"species": [{"element": "Mg", "occu": 1}], "abc": [0.375, 0.375, 0.125], "properties": {}, "label": "Mg", "xyz": [6.079326168750001, 6.079326168750001, 2.02644205625]}, {"species": [{"element": "Mg", "occu": 1}], "abc": [0.375, 0.375, 0.625], "properties": {}, "label": "Mg", "xyz": [6.079326168750001, 6.079326168750001, 10.13221028125]}, {"species": [{"element": "Mg", "occu": 1}], "abc": [0.375, 0.875, 0.125], "properties": {}, "label": "Mg", "xyz": [6.079326168750001, 14.185094393750001, 2.02644205625]}, {"species": [{"element": "Mg", "occu": 1}], "abc": [0.375, 0.875, 0.625], "properties": {}, "label": "Mg", "xyz": [6.079326168750001, 14.185094393750001, 10.13221028125]}, {"species": [{"element": "Mg", "occu": 1}], "abc": [0.875, 0.375, 0.125], "properties": {}, "label": "Mg", "xyz": [14.185094393750001, 6.079326168750001, 2.02644205625]}, {"species": [{"element": "Mg", "occu": 1}], "abc": [0.875, 0.375, 0.625], "properties": {}, "label": "Mg", "xyz": [14.185094393750001, 6.079326168750001, 10.13221028125]}, {"species": [{"element": "Mg", "occu": 1}], "abc": [0.875, 0.875, 0.125], "properties": {}, "label": "Mg", "xyz": [14.185094393750001, 14.185094393750001, 2.02644205625]}, {"species": [{"element": "Mg", "occu": 1}], "abc": [0.875, 0.875, 0.625], "properties": {}, "label": "Mg", "xyz": [14.185094393750001, 14.185094393750001, 10.13221028125]}, {"species": [{"element": "Mg", "occu": 1}], "abc": [0.375, 0.125, 0.375], "properties": {}, "label": "Mg", "xyz": [6.079326168750001, 2.02644205625, 6.079326168750001]}, {"species": [{"element": "Mg", "occu": 1}], "abc": [0.375, 0.125, 0.875], "properties": {}, "label": "Mg", "xyz": [6.079326168750001, 2.02644205625, 14.185094393750001]}, {"species": [{"element": "Mg", "occu": 1}], "abc": [0.375, 0.625, 0.375], "properties": {}, "label": "Mg", "xyz": [6.079326168750001, 10.13221028125, 6.079326168750001]}, {"species": [{"element": "Mg", "occu": 1}], "abc": [0.375, 0.625, 0.875], "properties": {}, "label": "Mg", "xyz": [6.079326168750001, 10.13221028125, 14.185094393750001]}, {"species": [{"element": "Mg", "occu": 1}], "abc": [0.875, 0.125, 0.375], "properties": {}, "label": "Mg", "xyz": [14.185094393750001, 2.02644205625, 6.079326168750001]}, {"species": [{"element": "Mg", "occu": 1}], "abc": [0.875, 0.125, 0.875], "properties": {}, "label": "Mg", "xyz": [14.185094393750001, 2.02644205625, 14.185094393750001]}, {"species": [{"element": "Mg", "occu": 1}], "abc": [0.875, 0.625, 0.375], "properties": {}, "label": "Mg", "xyz": [14.185094393750001, 10.13221028125, 6.079326168750001]}, {"species": [{"element": "Mg", "occu": 1}], "abc": [0.875, 0.625, 0.875], "properties": {}, "label": "Mg", "xyz": [14.185094393750001, 10.13221028125, 14.185094393750001]}, {"species": [{"element": "Mg", "occu": 1}], "abc": [0.125, 0.375, 0.375], "properties": {}, "label": "Mg", "xyz": [2.02644205625, 6.079326168750001, 6.079326168750001]}, {"species": [{"element": "Mg", "occu": 1}], "abc": [0.125, 0.375, 0.875], "properties": {}, "label": "Mg", "xyz": [2.02644205625, 6.079326168750001, 14.185094393750001]}, {"species": [{"element": "Mg", "occu": 1}], "abc": [0.125, 0.875, 0.375], "properties": {}, "label": "Mg", "xyz": [2.02644205625, 14.185094393750001, 6.079326168750001]}, {"species": [{"element": "Mg", "occu": 1}], "abc": [0.125, 0.875, 0.875], "properties": {}, "label": "Mg", "xyz": [2.02644205625, 14.185094393750001, 14.185094393750001]}, {"species": [{"element": "Mg", "occu": 1}], "abc": [0.625, 0.375, 0.375], "properties": {}, "label": "Mg", "xyz": [10.13221028125, 6.079326168750001, 6.079326168750001]}, {"species": [{"element": "Mg", "occu": 1}], "abc": [0.625, 0.375, 0.875], "properties": {}, "label": "Mg", "xyz": [10.13221028125, 6.079326168750001, 14.185094393750001]}, {"species": [{"element": "Mg", "occu": 1}], "abc": [0.625, 0.875, 0.375], "properties": {}, "label": "Mg", "xyz": [10.13221028125, 14.185094393750001, 6.079326168750001]}, {"species": [{"element": "Mg", "occu": 1}], "abc": [0.625, 0.875, 0.875], "properties": {}, "label": "Mg", "xyz": [10.13221028125, 14.185094393750001, 14.185094393750001]}, {"species": [{"element": "Mg", "occu": 1}], "abc": [0.0, 0.0, 0.0], "properties": {}, "label": "Mg", "xyz": [0.0, 0.0, 0.0]}, {"species": [{"element": "Mg", "occu": 1}], "abc": [0.0, 0.0, 0.5], "properties": {}, "label": "Mg", "xyz": [0.0, 0.0, 8.105768225]}, {"species": [{"element": "Mg", "occu": 1}], "abc": [0.0, 0.5, 0.0], "properties": {}, "label": "Mg", "xyz": [0.0, 8.105768225, 0.0]}, {"species": [{"element": "Mg", "occu": 1}], "abc": [0.0, 0.5, 0.5], "properties": {}, "label": "Mg", "xyz": [0.0, 8.105768225, 8.105768225]}, {"species": [{"element": "Mg", "occu": 1}], "abc": [0.5, 0.0, 0.0], "properties": {}, "label": "Mg", "xyz": [8.105768225, 0.0, 0.0]}, {"species": [{"element": "Mg", "occu": 1}], "abc": [0.5, 0.0, 0.5], "properties": {}, "label": "Mg", "xyz": [8.105768225, 0.0, 8.105768225]}, {"species": [{"element": "Mg", "occu": 1}], "abc": [0.5, 0.5, 0.0], "properties": {}, "label": "Mg", "xyz": [8.105768225, 8.105768225, 0.0]}, {"species": [{"element": "Mg", "occu": 1}], "abc": [0.5, 0.5, 0.5], "properties": {}, "label": "Mg", "xyz": [8.105768225, 8.105768225, 8.105768225]}, {"species": [{"element": "Mg", "occu": 1}], "abc": [0.25, 0.25, 0.0], "properties": {}, "label": "Mg", "xyz": [4.0528841125, 4.0528841125, 0.0]}, {"species": [{"element": "Mg", "occu": 1}], "abc": [0.25, 0.25, 0.5], "properties": {}, "label": "Mg", "xyz": [4.0528841125, 4.0528841125, 8.105768225]}, {"species": [{"element": "Mg", "occu": 1}], "abc": [0.25, 0.75, 0.0], "properties": {}, "label": "Mg", "xyz": [4.0528841125, 12.158652337500001, 0.0]}, {"species": [{"element": "Mg", "occu": 1}], "abc": [0.25, 0.75, 0.5], "properties": {}, "label": "Mg", "xyz": [4.0528841125, 12.158652337500001, 8.105768225]}, {"species": [{"element": "Mg", "occu": 1}], "abc": [0.75, 0.25, 0.0], "properties": {}, "label": "Mg", "xyz": [12.158652337500001, 4.0528841125, 0.0]}, {"species": [{"element": "Mg", "occu": 1}], "abc": [0.75, 0.25, 0.5], "properties": {}, "label": "Mg", "xyz": [12.158652337500001, 4.0528841125, 8.105768225]}, {"species": [{"element": "Mg", "occu": 1}], "abc": [0.75, 0.75, 0.0], "properties": {}, "label": "Mg", "xyz": [12.158652337500001, 12.158652337500001, 0.0]}, {"species": [{"element": "Mg", "occu": 1}], "abc": [0.75, 0.75, 0.5], "properties": {}, "label": "Mg", "xyz": [12.158652337500001, 12.158652337500001, 8.105768225]}, {"species": [{"element": "Mg", "occu": 1}], "abc": [0.25, 0.0, 0.25], "properties": {}, "label": "Mg", "xyz": [4.0528841125, 0.0, 4.0528841125]}, {"species": [{"element": "Mg", "occu": 1}], "abc": [0.25, 0.0, 0.75], "properties": {}, "label": "Mg", "xyz": [4.0528841125, 0.0, 12.158652337500001]}, {"species": [{"element": "Mg", "occu": 1}], "abc": [0.25, 0.5, 0.25], "properties": {}, "label": "Mg", "xyz": [4.0528841125, 8.105768225, 4.0528841125]}, {"species": [{"element": "Mg", "occu": 1}], "abc": [0.25, 0.5, 0.75], "properties": {}, "label": "Mg", "xyz": [4.0528841125, 8.105768225, 12.158652337500001]}, {"species": [{"element": "Mg", "occu": 1}], "abc": [0.75, 0.0, 0.25], "properties": {}, "label": "Mg", "xyz": [12.158652337500001, 0.0, 4.0528841125]}, {"species": [{"element": "Mg", "occu": 1}], "abc": [0.75, 0.0, 0.75], "properties": {}, "label": "Mg", "xyz": [12.158652337500001, 0.0, 12.158652337500001]}, {"species": [{"element": "Mg", "occu": 1}], "abc": [0.75, 0.5, 0.25], "properties": {}, "label": "Mg", "xyz": [12.158652337500001, 8.105768225, 4.0528841125]}, {"species": [{"element": "Mg", "occu": 1}], "abc": [0.75, 0.5, 0.75], "properties": {}, "label": "Mg", "xyz": [12.158652337500001, 8.105768225, 12.158652337500001]}, {"species": [{"element": "Mg", "occu": 1}], "abc": [0.0, 0.25, 0.25], "properties": {}, "label": "Mg", "xyz": [0.0, 4.0528841125, 4.0528841125]}, {"species": [{"element": "Mg", "occu": 1}], "abc": [0.0, 0.25, 0.75], "properties": {}, "label": "Mg", "xyz": [0.0, 4.0528841125, 12.158652337500001]}, {"species": [{"element": "Mg", "occu": 1}], "abc": [0.0, 0.75, 0.25], "properties": {}, "label": "Mg", "xyz": [0.0, 12.158652337500001, 4.0528841125]}, {"species": [{"element": "Mg", "occu": 1}], "abc": [0.0, 0.75, 0.75], "properties": {}, "label": "Mg", "xyz": [0.0, 12.158652337500001, 12.158652337500001]}, {"species": [{"element": "Mg", "occu": 1}], "abc": [0.5, 0.25, 0.25], "properties": {}, "label": "Mg", "xyz": [8.105768225, 4.0528841125, 4.0528841125]}, {"species": [{"element": "Mg", "occu": 1}], "abc": [0.5, 0.25, 0.75], "properties": {}, "label": "Mg", "xyz": [8.105768225, 4.0528841125, 12.158652337500001]}, {"species": [{"element": "Mg", "occu": 1}], "abc": [0.5, 0.75, 0.25], "properties": {}, "label": "Mg", "xyz": [8.105768225, 12.158652337500001, 4.0528841125]}, {"species": [{"element": "Mg", "occu": 1}], "abc": [0.5, 0.75, 0.75], "properties": {}, "label": "Mg", "xyz": [8.105768225, 12.158652337500001, 12.158652337500001]}, {"species": [{"element": "Al", "occu": 1}], "abc": [0.19425641919999848, 0.055743580800001406, 0.055743580800001406], "properties": {}, "label": "Al", "xyz": [3.149195020507255, 0.9036890919927429, 0.9036890919927429]}, {"species": [{"element": "Al", "occu": 1}], "abc": [0.3125, 0.1875, 0.1875], "properties": {}, "label": "Al", "xyz": [5.066105140625, 3.0396630843750003, 3.0396630843750003]}, {"species": [{"element": "Al", "occu": 1}], "abc": [0.3125, 0.1875, 0.6875], "properties": {}, "label": "Al", "xyz": [5.066105140625, 3.0396630843750003, 11.145431309375]}, {"species": [{"element": "Al", "occu": 1}], "abc": [0.3125, 0.6875, 0.1875], "properties": {}, "label": "Al", "xyz": [5.066105140625, 11.145431309375, 3.0396630843750003]}, {"species": [{"element": "Al", "occu": 1}], "abc": [0.3125, 0.6875, 0.6875], "properties": {}, "label": "Al", "xyz": [5.066105140625, 11.145431309375, 11.145431309375]}, {"species": [{"element": "Al", "occu": 1}], "abc": [0.8125, 0.1875, 0.1875], "properties": {}, "label": "Al", "xyz": [13.171873365625, 3.0396630843750003, 3.0396630843750003]}, {"species": [{"element": "Al", "occu": 1}], "abc": [0.8125, 0.1875, 0.6875], "properties": {}, "label": "Al", "xyz": [13.171873365625, 3.0396630843750003, 11.145431309375]}, {"species": [{"element": "Al", "occu": 1}], "abc": [0.8125, 0.6875, 0.1875], "properties": {}, "label": "Al", "xyz": [13.171873365625, 11.145431309375, 3.0396630843750003]}, {"species": [{"element": "Al", "occu": 1}], "abc": [0.8125, 0.6875, 0.6875], "properties": {}, "label": "Al", "xyz": [13.171873365625, 11.145431309375, 11.145431309375]}, {"species": [{"element": "Al", "occu": 1}], "abc": [0.0625, 0.4375, 0.1875], "properties": {}, "label": "Al", "xyz": [1.013221028125, 7.0925471968750005, 3.0396630843750003]}, {"species": [{"element": "Al", "occu": 1}], "abc": [0.0625, 0.4375, 0.6875], "properties": {}, "label": "Al", "xyz": [1.013221028125, 7.0925471968750005, 11.145431309375]}, {"species": [{"element": "Al", "occu": 1}], "abc": [0.0625, 0.9375, 0.1875], "properties": {}, "label": "Al", "xyz": [1.013221028125, 15.198315421875, 3.0396630843750003]}, {"species": [{"element": "Al", "occu": 1}], "abc": [0.0625, 0.9375, 0.6875], "properties": {}, "label": "Al", "xyz": [1.013221028125, 15.198315421875, 11.145431309375]}, {"species": [{"element": "Al", "occu": 1}], "abc": [0.5625, 0.4375, 0.1875], "properties": {}, "label": "Al", "xyz": [9.118989253125001, 7.0925471968750005, 3.0396630843750003]}, {"species": [{"element": "Al", "occu": 1}], "abc": [0.5625, 0.4375, 0.6875], "properties": {}, "label": "Al", "xyz": [9.118989253125001, 7.0925471968750005, 11.145431309375]}, {"species": [{"element": "Al", "occu": 1}], "abc": [0.5625, 0.9375, 0.1875], "properties": {}, "label": "Al", "xyz": [9.118989253125001, 15.198315421875, 3.0396630843750003]}, {"species": [{"element": "Al", "occu": 1}], "abc": [0.5625, 0.9375, 0.6875], "properties": {}, "label": "Al", "xyz": [9.118989253125001, 15.198315421875, 11.145431309375]}, {"species": [{"element": "Al", "occu": 1}], "abc": [0.0625, 0.1875, 0.4375], "properties": {}, "label": "Al", "xyz": [1.013221028125, 3.0396630843750003, 7.0925471968750005]}, {"species": [{"element": "Al", "occu": 1}], "abc": [0.0625, 0.1875, 0.9375], "properties": {}, "label": "Al", "xyz": [1.013221028125, 3.0396630843750003, 15.198315421875]}, {"species": [{"element": "Al", "occu": 1}], "abc": [0.0625, 0.6875, 0.4375], "properties": {}, "label": "Al", "xyz": [1.013221028125, 11.145431309375, 7.0925471968750005]}, {"species": [{"element": "Al", "occu": 1}], "abc": [0.0625, 0.6875, 0.9375], "properties": {}, "label": "Al", "xyz": [1.013221028125, 11.145431309375, 15.198315421875]}, {"species": [{"element": "Al", "occu": 1}], "abc": [0.5625, 0.1875, 0.4375], "properties": {}, "label": "Al", "xyz": [9.118989253125001, 3.0396630843750003, 7.0925471968750005]}, {"species": [{"element": "Al", "occu": 1}], "abc": [0.5625, 0.1875, 0.9375], "properties": {}, "label": "Al", "xyz": [9.118989253125001, 3.0396630843750003, 15.198315421875]}, {"species": [{"element": "Al", "occu": 1}], "abc": [0.5625, 0.6875, 0.4375], "properties": {}, "label": "Al", "xyz": [9.118989253125001, 11.145431309375, 7.0925471968750005]}, {"species": [{"element": "Al", "occu": 1}], "abc": [0.5625, 0.6875, 0.9375], "properties": {}, "label": "Al", "xyz": [9.118989253125001, 11.145431309375, 15.198315421875]}, {"species": [{"element": "Al", "occu": 1}], "abc": [0.3125, 0.4375, 0.4375], "properties": {}, "label": "Al", "xyz": [5.066105140625, 7.0925471968750005, 7.0925471968750005]}, {"species": [{"element": "Al", "occu": 1}], "abc": [0.3125, 0.4375, 0.9375], "properties": {}, "label": "Al", "xyz": [5.066105140625, 7.0925471968750005, 15.198315421875]}, {"species": [{"element": "Al", "occu": 1}], "abc": [0.3125, 0.9375, 0.4375], "properties": {}, "label": "Al", "xyz": [5.066105140625, 15.198315421875, 7.0925471968750005]}, {"species": [{"element": "Al", "occu": 1}], "abc": [0.3125, 0.9375, 0.9375], "properties": {}, "label": "Al", "xyz": [5.066105140625, 15.198315421875, 15.198315421875]}, {"species": [{"element": "Al", "occu": 1}], "abc": [0.8125, 0.4375, 0.4375], "properties": {}, "label": "Al", "xyz": [13.171873365625, 7.0925471968750005, 7.0925471968750005]}, {"species": [{"element": "Al", "occu": 1}], "abc": [0.8125, 0.4375, 0.9375], "properties": {}, "label": "Al", "xyz": [13.171873365625, 7.0925471968750005, 15.198315421875]}, {"species": [{"element": "Al", "occu": 1}], "abc": [0.8125, 0.9375, 0.4375], "properties": {}, "label": "Al", "xyz": [13.171873365625, 15.198315421875, 7.0925471968750005]}, {"species": [{"element": "Al", "occu": 1}], "abc": [0.8125, 0.9375, 0.9375], "properties": {}, "label": "Al", "xyz": [13.171873365625, 15.198315421875, 15.198315421875]}, {"species": [{"element": "Al", "occu": 1}], "abc": [0.3125, 0.3125, 0.3125], "properties": {}, "label": "Al", "xyz": [5.066105140625, 5.066105140625, 5.066105140625]}, {"species": [{"element": "Al", "occu": 1}], "abc": [0.3125, 0.3125, 0.8125], "properties": {}, "label": "Al", "xyz": [5.066105140625, 5.066105140625, 13.171873365625]}, {"species": [{"element": "Al", "occu": 1}], "abc": [0.3125, 0.8125, 0.3125], "properties": {}, "label": "Al", "xyz": [5.066105140625, 13.171873365625, 5.066105140625]}, {"species": [{"element": "Al", "occu": 1}], "abc": [0.3125, 0.8125, 0.8125], "properties": {}, "label": "Al", "xyz": [5.066105140625, 13.171873365625, 13.171873365625]}, {"species": [{"element": "Al", "occu": 1}], "abc": [0.8125, 0.3125, 0.3125], "properties": {}, "label": "Al", "xyz": [13.171873365625, 5.066105140625, 5.066105140625]}, {"species": [{"element": "Al", "occu": 1}], "abc": [0.8125, 0.3125, 0.8125], "properties": {}, "label": "Al", "xyz": [13.171873365625, 5.066105140625, 13.171873365625]}, {"species": [{"element": "Al", "occu": 1}], "abc": [0.8125, 0.8125, 0.3125], "properties": {}, "label": "Al", "xyz": [13.171873365625, 13.171873365625, 5.066105140625]}, {"species": [{"element": "Al", "occu": 1}], "abc": [0.8125, 0.8125, 0.8125], "properties": {}, "label": "Al", "xyz": [13.171873365625, 13.171873365625, 13.171873365625]}, {"species": [{"element": "Al", "occu": 1}], "abc": [0.0625, 0.0625, 0.3125], "properties": {}, "label": "Al", "xyz": [1.013221028125, 1.013221028125, 5.066105140625]}, {"species": [{"element": "Al", "occu": 1}], "abc": [0.0625, 0.0625, 0.8125], "properties": {}, "label": "Al", "xyz": [1.013221028125, 1.013221028125, 13.171873365625]}, {"species": [{"element": "Al", "occu": 1}], "abc": [0.0625, 0.5625, 0.3125], "properties": {}, "label": "Al", "xyz": [1.013221028125, 9.118989253125001, 5.066105140625]}, {"species": [{"element": "Al", "occu": 1}], "abc": [0.0625, 0.5625, 0.8125], "properties": {}, "label": "Al", "xyz": [1.013221028125, 9.118989253125001, 13.171873365625]}, {"species": [{"element": "Al", "occu": 1}], "abc": [0.5625, 0.0625, 0.3125], "properties": {}, "label": "Al", "xyz": [9.118989253125001, 1.013221028125, 5.066105140625]}, {"species": [{"element": "Al", "occu": 1}], "abc": [0.5625, 0.0625, 0.8125], "properties": {}, "label": "Al", "xyz": [9.118989253125001, 1.013221028125, 13.171873365625]}, {"species": [{"element": "Al", "occu": 1}], "abc": [0.5625, 0.5625, 0.3125], "properties": {}, "label": "Al", "xyz": [9.118989253125001, 9.118989253125001, 5.066105140625]}, {"species": [{"element": "Al", "occu": 1}], "abc": [0.5625, 0.5625, 0.8125], "properties": {}, "label": "Al", "xyz": [9.118989253125001, 9.118989253125001, 13.171873365625]}, {"species": [{"element": "Al", "occu": 1}], "abc": [0.0625, 0.3125, 0.0625], "properties": {}, "label": "Al", "xyz": [1.013221028125, 5.066105140625, 1.013221028125]}, {"species": [{"element": "Al", "occu": 1}], "abc": [0.0625, 0.3125, 0.5625], "properties": {}, "label": "Al", "xyz": [1.013221028125, 5.066105140625, 9.118989253125001]}, {"species": [{"element": "Al", "occu": 1}], "abc": [0.0625, 0.8125, 0.0625], "properties": {}, "label": "Al", "xyz": [1.013221028125, 13.171873365625, 1.013221028125]}, {"species": [{"element": "Al", "occu": 1}], "abc": [0.0625, 0.8125, 0.5625], "properties": {}, "label": "Al", "xyz": [1.013221028125, 13.171873365625, 9.118989253125001]}, {"species": [{"element": "Al", "occu": 1}], "abc": [0.5625, 0.3125, 0.0625], "properties": {}, "label": "Al", "xyz": [9.118989253125001, 5.066105140625, 1.013221028125]}, {"species": [{"element": "Al", "occu": 1}], "abc": [0.5625, 0.3125, 0.5625], "properties": {}, "label": "Al", "xyz": [9.118989253125001, 5.066105140625, 9.118989253125001]}, {"species": [{"element": "Al", "occu": 1}], "abc": [0.5625, 0.8125, 0.0625], "properties": {}, "label": "Al", "xyz": [9.118989253125001, 13.171873365625, 1.013221028125]}, {"species": [{"element": "Al", "occu": 1}], "abc": [0.5625, 0.8125, 0.5625], "properties": {}, "label": "Al", "xyz": [9.118989253125001, 13.171873365625, 9.118989253125001]}, {"species": [{"element": "Al", "occu": 1}], "abc": [0.3125, 0.0625, 0.0625], "properties": {}, "label": "Al", "xyz": [5.066105140625, 1.013221028125, 1.013221028125]}, {"species": [{"element": "Al", "occu": 1}], "abc": [0.3125, 0.0625, 0.5625], "properties": {}, "label": "Al", "xyz": [5.066105140625, 1.013221028125, 9.118989253125001]}, {"species": [{"element": "Al", "occu": 1}], "abc": [0.3125, 0.5625, 0.0625], "properties": {}, "label": "Al", "xyz": [5.066105140625, 9.118989253125001, 1.013221028125]}, {"species": [{"element": "Al", "occu": 1}], "abc": [0.3125, 0.5625, 0.5625], "properties": {}, "label": "Al", "xyz": [5.066105140625, 9.118989253125001, 9.118989253125001]}, {"species": [{"element": "Al", "occu": 1}], "abc": [0.8125, 0.0625, 0.0625], "properties": {}, "label": "Al", "xyz": [13.171873365625, 1.013221028125, 1.013221028125]}, {"species": [{"element": "Al", "occu": 1}], "abc": [0.8125, 0.0625, 0.5625], "properties": {}, "label": "Al", "xyz": [13.171873365625, 1.013221028125, 9.118989253125001]}, {"species": [{"element": "Al", "occu": 1}], "abc": [0.8125, 0.5625, 0.0625], "properties": {}, "label": "Al", "xyz": [13.171873365625, 9.118989253125001, 1.013221028125]}, {"species": [{"element": "Al", "occu": 1}], "abc": [0.8125, 0.5625, 0.5625], "properties": {}, "label": "Al", "xyz": [13.171873365625, 9.118989253125001, 9.118989253125001]}, {"species": [{"element": "Al", "occu": 1}], "abc": [0.1875, 0.3125, 0.18749999999999994], "properties": {}, "label": "Al", "xyz": [3.0396630843750003, 5.066105140625, 3.039663084374999]}, {"species": [{"element": "Al", "occu": 1}], "abc": [0.1875, 0.3125, 0.6874999999999999], "properties": {}, "label": "Al", "xyz": [3.0396630843750003, 5.066105140625, 11.145431309374999]}, {"species": [{"element": "Al", "occu": 1}], "abc": [0.1875, 0.8125, 0.18749999999999994], "properties": {}, "label": "Al", "xyz": [3.0396630843750003, 13.171873365625, 3.039663084374999]}, {"species": [{"element": "Al", "occu": 1}], "abc": [0.1875, 0.8125, 0.6874999999999999], "properties": {}, "label": "Al", "xyz": [3.0396630843750003, 13.171873365625, 11.145431309374999]}, {"species": [{"element": "Al", "occu": 1}], "abc": [0.6875, 0.3125, 0.18749999999999994], "properties": {}, "label": "Al", "xyz": [11.145431309375, 5.066105140625, 3.039663084374999]}, {"species": [{"element": "Al", "occu": 1}], "abc": [0.6875, 0.3125, 0.6874999999999999], "properties": {}, "label": "Al", "xyz": [11.145431309375, 5.066105140625, 11.145431309374999]}, {"species": [{"element": "Al", "occu": 1}], "abc": [0.6875, 0.8125, 0.18749999999999994], "properties": {}, "label": "Al", "xyz": [11.145431309375, 13.171873365625, 3.039663084374999]}, {"species": [{"element": "Al", "occu": 1}], "abc": [0.6875, 0.8125, 0.6874999999999999], "properties": {}, "label": "Al", "xyz": [11.145431309375, 13.171873365625, 11.145431309374999]}, {"species": [{"element": "Al", "occu": 1}], "abc": [0.4375, 0.0625, 0.18749999999999994], "properties": {}, "label": "Al", "xyz": [7.0925471968750005, 1.013221028125, 3.039663084374999]}, {"species": [{"element": "Al", "occu": 1}], "abc": [0.4375, 0.0625, 0.6874999999999999], "properties": {}, "label": "Al", "xyz": [7.0925471968750005, 1.013221028125, 11.145431309374999]}, {"species": [{"element": "Al", "occu": 1}], "abc": [0.4375, 0.5625, 0.18749999999999994], "properties": {}, "label": "Al", "xyz": [7.0925471968750005, 9.118989253125001, 3.039663084374999]}, {"species": [{"element": "Al", "occu": 1}], "abc": [0.4375, 0.5625, 0.6874999999999999], "properties": {}, "label": "Al", "xyz": [7.0925471968750005, 9.118989253125001, 11.145431309374999]}, {"species": [{"element": "Al", "occu": 1}], "abc": [0.9375, 0.0625, 0.18749999999999994], "properties": {}, "label": "Al", "xyz": [15.198315421875, 1.013221028125, 3.039663084374999]}, {"species": [{"element": "Al", "occu": 1}], "abc": [0.9375, 0.0625, 0.6874999999999999], "properties": {}, "label": "Al", "xyz": [15.198315421875, 1.013221028125, 11.145431309374999]}, {"species": [{"element": "Al", "occu": 1}], "abc": [0.9375, 0.5625, 0.18749999999999994], "properties": {}, "label": "Al", "xyz": [15.198315421875, 9.118989253125001, 3.039663084374999]}, {"species": [{"element": "Al", "occu": 1}], "abc": [0.9375, 0.5625, 0.6874999999999999], "properties": {}, "label": "Al", "xyz": [15.198315421875, 9.118989253125001, 11.145431309374999]}, {"species": [{"element": "Al", "occu": 1}], "abc": [0.4375, 0.3125, 0.43749999999999994], "properties": {}, "label": "Al", "xyz": [7.0925471968750005, 5.066105140625, 7.092547196875]}, {"species": [{"element": "Al", "occu": 1}], "abc": [0.4375, 0.3125, 0.9374999999999999], "properties": {}, "label": "Al", "xyz": [7.0925471968750005, 5.066105140625, 15.198315421874998]}, {"species": [{"element": "Al", "occu": 1}], "abc": [0.4375, 0.8125, 0.43749999999999994], "properties": {}, "label": "Al", "xyz": [7.0925471968750005, 13.171873365625, 7.092547196875]}, {"species": [{"element": "Al", "occu": 1}], "abc": [0.4375, 0.8125, 0.9374999999999999], "properties": {}, "label": "Al", "xyz": [7.0925471968750005, 13.171873365625, 15.198315421874998]}, {"species": [{"element": "Al", "occu": 1}], "abc": [0.9375, 0.3125, 0.43749999999999994], "properties": {}, "label": "Al", "xyz": [15.198315421875, 5.066105140625, 7.092547196875]}, {"species": [{"element": "Al", "occu": 1}], "abc": [0.9375, 0.3125, 0.9374999999999999], "properties": {}, "label": "Al", "xyz": [15.198315421875, 5.066105140625, 15.198315421874998]}, {"species": [{"element": "Al", "occu": 1}], "abc": [0.9375, 0.8125, 0.43749999999999994], "properties": {}, "label": "Al", "xyz": [15.198315421875, 13.171873365625, 7.092547196875]}, {"species": [{"element": "Al", "occu": 1}], "abc": [0.9375, 0.8125, 0.9374999999999999], "properties": {}, "label": "Al", "xyz": [15.198315421875, 13.171873365625, 15.198315421874998]}, {"species": [{"element": "Al", "occu": 1}], "abc": [0.1875, 0.0625, 0.43749999999999994], "properties": {}, "label": "Al", "xyz": [3.0396630843750003, 1.013221028125, 7.092547196875]}, {"species": [{"element": "Al", "occu": 1}], "abc": [0.1875, 0.0625, 0.9374999999999999], "properties": {}, "label": "Al", "xyz": [3.0396630843750003, 1.013221028125, 15.198315421874998]}, {"species": [{"element": "Al", "occu": 1}], "abc": [0.1875, 0.5625, 0.43749999999999994], "properties": {}, "label": "Al", "xyz": [3.0396630843750003, 9.118989253125001, 7.092547196875]}, {"species": [{"element": "Al", "occu": 1}], "abc": [0.1875, 0.5625, 0.9374999999999999], "properties": {}, "label": "Al", "xyz": [3.0396630843750003, 9.118989253125001, 15.198315421874998]}, {"species": [{"element": "Al", "occu": 1}], "abc": [0.6875, 0.0625, 0.43749999999999994], "properties": {}, "label": "Al", "xyz": [11.145431309375, 1.013221028125, 7.092547196875]}, {"species": [{"element": "Al", "occu": 1}], "abc": [0.6875, 0.0625, 0.9374999999999999], "properties": {}, "label": "Al", "xyz": [11.145431309375, 1.013221028125, 15.198315421874998]}, {"species": [{"element": "Al", "occu": 1}], "abc": [0.6875, 0.5625, 0.43749999999999994], "properties": {}, "label": "Al", "xyz": [11.145431309375, 9.118989253125001, 7.092547196875]}, {"species": [{"element": "Al", "occu": 1}], "abc": [0.6875, 0.5625, 0.9374999999999999], "properties": {}, "label": "Al", "xyz": [11.145431309375, 9.118989253125001, 15.198315421874998]}, {"species": [{"element": "Al", "occu": 1}], "abc": [0.18749999999999994, 0.18749999999999994, 0.3125], "properties": {}, "label": "Al", "xyz": [3.039663084374999, 3.039663084374999, 5.066105140625]}, {"species": [{"element": "Al", "occu": 1}], "abc": [0.18749999999999994, 0.18749999999999994, 0.8125], "properties": {}, "label": "Al", "xyz": [3.039663084374999, 3.039663084374999, 13.171873365625]}, {"species": [{"element": "Al", "occu": 1}], "abc": [0.18749999999999994, 0.6874999999999999, 0.3125], "properties": {}, "label": "Al", "xyz": [3.039663084374999, 11.145431309374999, 5.066105140625]}, {"species": [{"element": "Al", "occu": 1}], "abc": [0.18749999999999994, 0.6874999999999999, 0.8125], "properties": {}, "label": "Al", "xyz": [3.039663084374999, 11.145431309374999, 13.171873365625]}, {"species": [{"element": "Al", "occu": 1}], "abc": [0.6874999999999999, 0.18749999999999994, 0.3125], "properties": {}, "label": "Al", "xyz": [11.145431309374999, 3.039663084374999, 5.066105140625]}, {"species": [{"element": "Al", "occu": 1}], "abc": [0.6874999999999999, 0.18749999999999994, 0.8125], "properties": {}, "label": "Al", "xyz": [11.145431309374999, 3.039663084374999, 13.171873365625]}, {"species": [{"element": "Al", "occu": 1}], "abc": [0.6874999999999999, 0.6874999999999999, 0.3125], "properties": {}, "label": "Al", "xyz": [11.145431309374999, 11.145431309374999, 5.066105140625]}, {"species": [{"element": "Al", "occu": 1}], "abc": [0.6874999999999999, 0.6874999999999999, 0.8125], "properties": {}, "label": "Al", "xyz": [11.145431309374999, 11.145431309374999, 13.171873365625]}, {"species": [{"element": "Al", "occu": 1}], "abc": [0.43749999999999994, 0.43749999999999994, 0.3125], "properties": {}, "label": "Al", "xyz": [7.092547196875, 7.092547196875, 5.066105140625]}, {"species": [{"element": "Al", "occu": 1}], "abc": [0.43749999999999994, 0.43749999999999994, 0.8125], "properties": {}, "label": "Al", "xyz": [7.092547196875, 7.092547196875, 13.171873365625]}, {"species": [{"element": "Al", "occu": 1}], "abc": [0.43749999999999994, 0.9374999999999999, 0.3125], "properties": {}, "label": "Al", "xyz": [7.092547196875, 15.198315421874998, 5.066105140625]}, {"species": [{"element": "Al", "occu": 1}], "abc": [0.43749999999999994, 0.9374999999999999, 0.8125], "properties": {}, "label": "Al", "xyz": [7.092547196875, 15.198315421874998, 13.171873365625]}, {"species": [{"element": "Al", "occu": 1}], "abc": [0.9374999999999999, 0.43749999999999994, 0.3125], "properties": {}, "label": "Al", "xyz": [15.198315421874998, 7.092547196875, 5.066105140625]}, {"species": [{"element": "Al", "occu": 1}], "abc": [0.9374999999999999, 0.43749999999999994, 0.8125], "properties": {}, "label": "Al", "xyz": [15.198315421874998, 7.092547196875, 13.171873365625]}, {"species": [{"element": "Al", "occu": 1}], "abc": [0.9374999999999999, 0.9374999999999999, 0.3125], "properties": {}, "label": "Al", "xyz": [15.198315421874998, 15.198315421874998, 5.066105140625]}, {"species": [{"element": "Al", "occu": 1}], "abc": [0.9374999999999999, 0.9374999999999999, 0.8125], "properties": {}, "label": "Al", "xyz": [15.198315421874998, 15.198315421874998, 13.171873365625]}, {"species": [{"element": "Al", "occu": 1}], "abc": [0.43749999999999994, 0.18749999999999994, 0.0625], "properties": {}, "label": "Al", "xyz": [7.092547196875, 3.039663084374999, 1.013221028125]}, {"species": [{"element": "Al", "occu": 1}], "abc": [0.43749999999999994, 0.18749999999999994, 0.5625], "properties": {}, "label": "Al", "xyz": [7.092547196875, 3.039663084374999, 9.118989253125001]}, {"species": [{"element": "Al", "occu": 1}], "abc": [0.43749999999999994, 0.6874999999999999, 0.0625], "properties": {}, "label": "Al", "xyz": [7.092547196875, 11.145431309374999, 1.013221028125]}, {"species": [{"element": "Al", "occu": 1}], "abc": [0.43749999999999994, 0.6874999999999999, 0.5625], "properties": {}, "label": "Al", "xyz": [7.092547196875, 11.145431309374999, 9.118989253125001]}, {"species": [{"element": "Al", "occu": 1}], "abc": [0.9374999999999999, 0.18749999999999994, 0.0625], "properties": {}, "label": "Al", "xyz": [15.198315421874998, 3.039663084374999, 1.013221028125]}, {"species": [{"element": "Al", "occu": 1}], "abc": [0.9374999999999999, 0.18749999999999994, 0.5625], "properties": {}, "label": "Al", "xyz": [15.198315421874998, 3.039663084374999, 9.118989253125001]}, {"species": [{"element": "Al", "occu": 1}], "abc": [0.9374999999999999, 0.6874999999999999, 0.0625], "properties": {}, "label": "Al", "xyz": [15.198315421874998, 11.145431309374999, 1.013221028125]}, {"species": [{"element": "Al", "occu": 1}], "abc": [0.9374999999999999, 0.6874999999999999, 0.5625], "properties": {}, "label": "Al", "xyz": [15.198315421874998, 11.145431309374999, 9.118989253125001]}, {"species": [{"element": "Al", "occu": 1}], "abc": [0.18749999999999994, 0.43749999999999994, 0.0625], "properties": {}, "label": "Al", "xyz": [3.039663084374999, 7.092547196875, 1.013221028125]}, {"species": [{"element": "Al", "occu": 1}], "abc": [0.18749999999999994, 0.43749999999999994, 0.5625], "properties": {}, "label": "Al", "xyz": [3.039663084374999, 7.092547196875, 9.118989253125001]}, {"species": [{"element": "Al", "occu": 1}], "abc": [0.18749999999999994, 0.9374999999999999, 0.0625], "properties": {}, "label": "Al", "xyz": [3.039663084374999, 15.198315421874998, 1.013221028125]}, {"species": [{"element": "Al", "occu": 1}], "abc": [0.18749999999999994, 0.9374999999999999, 0.5625], "properties": {}, "label": "Al", "xyz": [3.039663084374999, 15.198315421874998, 9.118989253125001]}, {"species": [{"element": "Al", "occu": 1}], "abc": [0.6874999999999999, 0.43749999999999994, 0.0625], "properties": {}, "label": "Al", "xyz": [11.145431309374999, 7.092547196875, 1.013221028125]}, {"species": [{"element": "Al", "occu": 1}], "abc": [0.6874999999999999, 0.43749999999999994, 0.5625], "properties": {}, "label": "Al", "xyz": [11.145431309374999, 7.092547196875, 9.118989253125001]}, {"species": [{"element": "Al", "occu": 1}], "abc": [0.6874999999999999, 0.9374999999999999, 0.0625], "properties": {}, "label": "Al", "xyz": [11.145431309374999, 15.198315421874998, 1.013221028125]}, {"species": [{"element": "Al", "occu": 1}], "abc": [0.6874999999999999, 0.9374999999999999, 0.5625], "properties": {}, "label": "Al", "xyz": [11.145431309374999, 15.198315421874998, 9.118989253125001]}, {"species": [{"element": "O", "occu": 1}], "abc": [0.4307435808000014, 0.4307435808000014, 0.4307435808000014], "properties": {}, "label": "O", "xyz": [6.983015260742743, 6.983015260742743, 6.983015260742743]}, {"species": [{"element": "O", "occu": 1}], "abc": [0.4307435808000014, 0.4307435808000014, 0.9307435808000014], "properties": {}, "label": "O", "xyz": [6.983015260742743, 6.983015260742743, 15.088783485742743]}, {"species": [{"element": "O", "occu": 1}], "abc": [0.4307435808000014, 0.9307435808000014, 0.4307435808000014], "properties": {}, "label": "O", "xyz": [6.983015260742743, 15.088783485742743, 6.983015260742743]}, {"species": [{"element": "O", "occu": 1}], "abc": [0.4307435808000014, 0.9307435808000014, 0.9307435808000014], "properties": {}, "label": "O", "xyz": [6.983015260742743, 15.088783485742743, 15.088783485742743]}, {"species": [{"element": "O", "occu": 1}], "abc": [0.9307435808000014, 0.4307435808000014, 0.4307435808000014], "properties": {}, "label": "O", "xyz": [15.088783485742743, 6.983015260742743, 6.983015260742743]}, {"species": [{"element": "O", "occu": 1}], "abc": [0.9307435808000014, 0.4307435808000014, 0.9307435808000014], "properties": {}, "label": "O", "xyz": [15.088783485742743, 6.983015260742743, 15.088783485742743]}, {"species": [{"element": "O", "occu": 1}], "abc": [0.9307435808000014, 0.9307435808000014, 0.4307435808000014], "properties": {}, "label": "O", "xyz": [15.088783485742743, 15.088783485742743, 6.983015260742743]}, {"species": [{"element": "O", "occu": 1}], "abc": [0.9307435808000014, 0.9307435808000014, 0.9307435808000014], "properties": {}, "label": "O", "xyz": [15.088783485742743, 15.088783485742743, 15.088783485742743]}, {"species": [{"element": "O", "occu": 1}], "abc": [0.18074358080000152, 0.18074358080000152, 0.4307435808000014], "properties": {}, "label": "O", "xyz": [2.930131148242745, 2.930131148242745, 6.983015260742743]}, {"species": [{"element": "O", "occu": 1}], "abc": [0.18074358080000152, 0.18074358080000152, 0.9307435808000014], "properties": {}, "label": "O", "xyz": [2.930131148242745, 2.930131148242745, 15.088783485742743]}, {"species": [{"element": "O", "occu": 1}], "abc": [0.18074358080000152, 0.6807435808000015, 0.4307435808000014], "properties": {}, "label": "O", "xyz": [2.930131148242745, 11.035899373242746, 6.983015260742743]}, {"species": [{"element": "O", "occu": 1}], "abc": [0.18074358080000152, 0.6807435808000015, 0.9307435808000014], "properties": {}, "label": "O", "xyz": [2.930131148242745, 11.035899373242746, 15.088783485742743]}, {"species": [{"element": "O", "occu": 1}], "abc": [0.6807435808000015, 0.18074358080000152, 0.4307435808000014], "properties": {}, "label": "O", "xyz": [11.035899373242746, 2.930131148242745, 6.983015260742743]}, {"species": [{"element": "O", "occu": 1}], "abc": [0.6807435808000015, 0.18074358080000152, 0.9307435808000014], "properties": {}, "label": "O", "xyz": [11.035899373242746, 2.930131148242745, 15.088783485742743]}, {"species": [{"element": "O", "occu": 1}], "abc": [0.6807435808000015, 0.6807435808000015, 0.4307435808000014], "properties": {}, "label": "O", "xyz": [11.035899373242746, 11.035899373242746, 6.983015260742743]}, {"species": [{"element": "O", "occu": 1}], "abc": [0.6807435808000015, 0.6807435808000015, 0.9307435808000014], "properties": {}, "label": "O", "xyz": [11.035899373242746, 11.035899373242746, 15.088783485742743]}, {"species": [{"element": "O", "occu": 1}], "abc": [0.18074358080000152, 0.4307435808000014, 0.18074358080000152], "properties": {}, "label": "O", "xyz": [2.930131148242745, 6.983015260742743, 2.930131148242745]}, {"species": [{"element": "O", "occu": 1}], "abc": [0.18074358080000152, 0.4307435808000014, 0.6807435808000015], "properties": {}, "label": "O", "xyz": [2.930131148242745, 6.983015260742743, 11.035899373242746]}, {"species": [{"element": "O", "occu": 1}], "abc": [0.18074358080000152, 0.9307435808000014, 0.18074358080000152], "properties": {}, "label": "O", "xyz": [2.930131148242745, 15.088783485742743, 2.930131148242745]}, {"species": [{"element": "O", "occu": 1}], "abc": [0.18074358080000152, 0.9307435808000014, 0.6807435808000015], "properties": {}, "label": "O", "xyz": [2.930131148242745, 15.088783485742743, 11.035899373242746]}, {"species": [{"element": "O", "occu": 1}], "abc": [0.6807435808000015, 0.4307435808000014, 0.18074358080000152], "properties": {}, "label": "O", "xyz": [11.035899373242746, 6.983015260742743, 2.930131148242745]}, {"species": [{"element": "O", "occu": 1}], "abc": [0.6807435808000015, 0.4307435808000014, 0.6807435808000015], "properties": {}, "label": "O", "xyz": [11.035899373242746, 6.983015260742743, 11.035899373242746]}, {"species": [{"element": "O", "occu": 1}], "abc": [0.6807435808000015, 0.9307435808000014, 0.18074358080000152], "properties": {}, "label": "O", "xyz": [11.035899373242746, 15.088783485742743, 2.930131148242745]}, {"species": [{"element": "O", "occu": 1}], "abc": [0.6807435808000015, 0.9307435808000014, 0.6807435808000015], "properties": {}, "label": "O", "xyz": [11.035899373242746, 15.088783485742743, 11.035899373242746]}, {"species": [{"element": "O", "occu": 1}], "abc": [0.4307435808000014, 0.18074358080000152, 0.18074358080000152], "properties": {}, "label": "O", "xyz": [6.983015260742743, 2.930131148242745, 2.930131148242745]}, {"species": [{"element": "O", "occu": 1}], "abc": [0.4307435808000014, 0.18074358080000152, 0.6807435808000015], "properties": {}, "label": "O", "xyz": [6.983015260742743, 2.930131148242745, 11.035899373242746]}, {"species": [{"element": "O", "occu": 1}], "abc": [0.4307435808000014, 0.6807435808000015, 0.18074358080000152], "properties": {}, "label": "O", "xyz": [6.983015260742743, 11.035899373242746, 2.930131148242745]}, {"species": [{"element": "O", "occu": 1}], "abc": [0.4307435808000014, 0.6807435808000015, 0.6807435808000015], "properties": {}, "label": "O", "xyz": [6.983015260742743, 11.035899373242746, 11.035899373242746]}, {"species": [{"element": "O", "occu": 1}], "abc": [0.9307435808000014, 0.18074358080000152, 0.18074358080000152], "properties": {}, "label": "O", "xyz": [15.088783485742743, 2.930131148242745, 2.930131148242745]}, {"species": [{"element": "O", "occu": 1}], "abc": [0.9307435808000014, 0.18074358080000152, 0.6807435808000015], "properties": {}, "label": "O", "xyz": [15.088783485742743, 2.930131148242745, 11.035899373242746]}, {"species": [{"element": "O", "occu": 1}], "abc": [0.9307435808000014, 0.6807435808000015, 0.18074358080000152], "properties": {}, "label": "O", "xyz": [15.088783485742743, 11.035899373242746, 2.930131148242745]}, {"species": [{"element": "O", "occu": 1}], "abc": [0.9307435808000014, 0.6807435808000015, 0.6807435808000015], "properties": {}, "label": "O", "xyz": [15.088783485742743, 11.035899373242746, 11.035899373242746]}, {"species": [{"element": "O", "occu": 1}], "abc": [0.19425641919999848, 0.3057435808000015, 0.3057435808000015], "properties": {}, "label": "O", "xyz": [3.149195020507255, 4.956573204492745, 4.956573204492745]}, {"species": [{"element": "O", "occu": 1}], "abc": [0.19425641919999848, 0.3057435808000015, 0.8057435808000015], "properties": {}, "label": "O", "xyz": [3.149195020507255, 4.956573204492745, 13.062341429492745]}, {"species": [{"element": "O", "occu": 1}], "abc": [0.19425641919999848, 0.8057435808000015, 0.3057435808000015], "properties": {}, "label": "O", "xyz": [3.149195020507255, 13.062341429492745, 4.956573204492745]}, {"species": [{"element": "O", "occu": 1}], "abc": [0.19425641919999848, 0.8057435808000015, 0.8057435808000015], "properties": {}, "label": "O", "xyz": [3.149195020507255, 13.062341429492745, 13.062341429492745]}, {"species": [{"element": "O", "occu": 1}], "abc": [0.6942564191999985, 0.3057435808000015, 0.3057435808000015], "properties": {}, "label": "O", "xyz": [11.254963245507255, 4.956573204492745, 4.956573204492745]}, {"species": [{"element": "O", "occu": 1}], "abc": [0.6942564191999985, 0.3057435808000015, 0.8057435808000015], "properties": {}, "label": "O", "xyz": [11.254963245507255, 4.956573204492745, 13.062341429492745]}, {"species": [{"element": "O", "occu": 1}], "abc": [0.6942564191999985, 0.8057435808000015, 0.3057435808000015], "properties": {}, "label": "O", "xyz": [11.254963245507255, 13.062341429492745, 4.956573204492745]}, {"species": [{"element": "O", "occu": 1}], "abc": [0.6942564191999985, 0.8057435808000015, 0.8057435808000015], "properties": {}, "label": "O", "xyz": [11.254963245507255, 13.062341429492745, 13.062341429492745]}, {"species": [{"element": "O", "occu": 1}], "abc": [0.4442564191999985, 0.055743580800001406, 0.3057435808000015], "properties": {}, "label": "O", "xyz": [7.202079133007255, 0.9036890919927429, 4.956573204492745]}, {"species": [{"element": "O", "occu": 1}], "abc": [0.4442564191999985, 0.055743580800001406, 0.8057435808000015], "properties": {}, "label": "O", "xyz": [7.202079133007255, 0.9036890919927429, 13.062341429492745]}, {"species": [{"element": "O", "occu": 1}], "abc": [0.4442564191999985, 0.5557435808000013, 0.3057435808000015], "properties": {}, "label": "O", "xyz": [7.202079133007255, 9.00945731699274, 4.956573204492745]}, {"species": [{"element": "O", "occu": 1}], "abc": [0.4442564191999985, 0.5557435808000013, 0.8057435808000015], "properties": {}, "label": "O", "xyz": [7.202079133007255, 9.00945731699274, 13.062341429492745]}, {"species": [{"element": "O", "occu": 1}], "abc": [0.9442564191999984, 0.055743580800001406, 0.3057435808000015], "properties": {}, "label": "O", "xyz": [15.307847358007255, 0.9036890919927429, 4.956573204492745]}, {"species": [{"element": "O", "occu": 1}], "abc": [0.9442564191999984, 0.055743580800001406, 0.8057435808000015], "properties": {}, "label": "O", "xyz": [15.307847358007255, 0.9036890919927429, 13.062341429492745]}, {"species": [{"element": "O", "occu": 1}], "abc": [0.9442564191999984, 0.5557435808000013, 0.3057435808000015], "properties": {}, "label": "O", "xyz": [15.307847358007255, 9.00945731699274, 4.956573204492745]}, {"species": [{"element": "O", "occu": 1}], "abc": [0.9442564191999984, 0.5557435808000013, 0.8057435808000015], "properties": {}, "label": "O", "xyz": [15.307847358007255, 9.00945731699274, 13.062341429492745]}, {"species": [{"element": "O", "occu": 1}], "abc": [0.4442564191999985, 0.3057435808000015, 0.055743580800001406], "properties": {}, "label": "O", "xyz": [7.202079133007255, 4.956573204492745, 0.9036890919927429]}, {"species": [{"element": "O", "occu": 1}], "abc": [0.4442564191999985, 0.3057435808000015, 0.5557435808000013], "properties": {}, "label": "O", "xyz": [7.202079133007255, 4.956573204492745, 9.00945731699274]}, {"species": [{"element": "O", "occu": 1}], "abc": [0.4442564191999985, 0.8057435808000015, 0.055743580800001406], "properties": {}, "label": "O", "xyz": [7.202079133007255, 13.062341429492745, 0.9036890919927429]}, {"species": [{"element": "O", "occu": 1}], "abc": [0.4442564191999985, 0.8057435808000015, 0.5557435808000013], "properties": {}, "label": "O", "xyz": [7.202079133007255, 13.062341429492745, 9.00945731699274]}, {"species": [{"element": "O", "occu": 1}], "abc": [0.9442564191999984, 0.3057435808000015, 0.055743580800001406], "properties": {}, "label": "O", "xyz": [15.307847358007255, 4.956573204492745, 0.9036890919927429]}, {"species": [{"element": "O", "occu": 1}], "abc": [0.9442564191999984, 0.3057435808000015, 0.5557435808000013], "properties": {}, "label": "O", "xyz": [15.307847358007255, 4.956573204492745, 9.00945731699274]}, {"species": [{"element": "O", "occu": 1}], "abc": [0.9442564191999984, 0.8057435808000015, 0.055743580800001406], "properties": {}, "label": "O", "xyz": [15.307847358007255, 13.062341429492745, 0.9036890919927429]}, {"species": [{"element": "O", "occu": 1}], "abc": [0.9442564191999984, 0.8057435808000015, 0.5557435808000013], "properties": {}, "label": "O", "xyz": [15.307847358007255, 13.062341429492745, 9.00945731699274]}, {"species": [{"element": "O", "occu": 1}], "abc": [0.19425641919999848, 0.055743580800001406, 0.5557435808000013], "properties": {}, "label": "O", "xyz": [3.149195020507255, 0.9036890919927429, 9.00945731699274]}, {"species": [{"element": "O", "occu": 1}], "abc": [0.19425641919999848, 0.5557435808000013, 0.055743580800001406], "properties": {}, "label": "O", "xyz": [3.149195020507255, 9.00945731699274, 0.9036890919927429]}, {"species": [{"element": "O", "occu": 1}], "abc": [0.19425641919999848, 0.5557435808000013, 0.5557435808000013], "properties": {}, "label": "O", "xyz": [3.149195020507255, 9.00945731699274, 9.00945731699274]}, {"species": [{"element": "O", "occu": 1}], "abc": [0.6942564191999985, 0.055743580800001406, 0.055743580800001406], "properties": {}, "label": "O", "xyz": [11.254963245507255, 0.9036890919927429, 0.9036890919927429]}, {"species": [{"element": "O", "occu": 1}], "abc": [0.6942564191999985, 0.055743580800001406, 0.5557435808000013], "properties": {}, "label": "O", "xyz": [11.254963245507255, 0.9036890919927429, 9.00945731699274]}, {"species": [{"element": "O", "occu": 1}], "abc": [0.6942564191999985, 0.5557435808000013, 0.055743580800001406], "properties": {}, "label": "O", "xyz": [11.254963245507255, 9.00945731699274, 0.9036890919927429]}, {"species": [{"element": "O", "occu": 1}], "abc": [0.6942564191999985, 0.5557435808000013, 0.5557435808000013], "properties": {}, "label": "O", "xyz": [11.254963245507255, 9.00945731699274, 9.00945731699274]}, {"species": [{"element": "O", "occu": 1}], "abc": [0.3057435808000015, 0.3057435808000015, 0.19425641919999848], "properties": {}, "label": "O", "xyz": [4.956573204492745, 4.956573204492745, 3.149195020507255]}, {"species": [{"element": "O", "occu": 1}], "abc": [0.3057435808000015, 0.3057435808000015, 0.6942564191999985], "properties": {}, "label": "O", "xyz": [4.956573204492745, 4.956573204492745, 11.254963245507255]}, {"species": [{"element": "O", "occu": 1}], "abc": [0.3057435808000015, 0.8057435808000015, 0.19425641919999848], "properties": {}, "label": "O", "xyz": [4.956573204492745, 13.062341429492745, 3.149195020507255]}, {"species": [{"element": "O", "occu": 1}], "abc": [0.3057435808000015, 0.8057435808000015, 0.6942564191999985], "properties": {}, "label": "O", "xyz": [4.956573204492745, 13.062341429492745, 11.254963245507255]}, {"species": [{"element": "O", "occu": 1}], "abc": [0.8057435808000015, 0.3057435808000015, 0.19425641919999848], "properties": {}, "label": "O", "xyz": [13.062341429492745, 4.956573204492745, 3.149195020507255]}, {"species": [{"element": "O", "occu": 1}], "abc": [0.8057435808000015, 0.3057435808000015, 0.6942564191999985], "properties": {}, "label": "O", "xyz": [13.062341429492745, 4.956573204492745, 11.254963245507255]}, {"species": [{"element": "O", "occu": 1}], "abc": [0.8057435808000015, 0.8057435808000015, 0.19425641919999848], "properties": {}, "label": "O", "xyz": [13.062341429492745, 13.062341429492745, 3.149195020507255]}, {"species": [{"element": "O", "occu": 1}], "abc": [0.8057435808000015, 0.8057435808000015, 0.6942564191999985], "properties": {}, "label": "O", "xyz": [13.062341429492745, 13.062341429492745, 11.254963245507255]}, {"species": [{"element": "O", "occu": 1}], "abc": [0.055743580800001406, 0.055743580800001406, 0.19425641919999848], "properties": {}, "label": "O", "xyz": [0.9036890919927429, 0.9036890919927429, 3.149195020507255]}, {"species": [{"element": "O", "occu": 1}], "abc": [0.055743580800001406, 0.055743580800001406, 0.6942564191999985], "properties": {}, "label": "O", "xyz": [0.9036890919927429, 0.9036890919927429, 11.254963245507255]}, {"species": [{"element": "O", "occu": 1}], "abc": [0.055743580800001406, 0.5557435808000013, 0.19425641919999848], "properties": {}, "label": "O", "xyz": [0.9036890919927429, 9.00945731699274, 3.149195020507255]}, {"species": [{"element": "O", "occu": 1}], "abc": [0.055743580800001406, 0.5557435808000013, 0.6942564191999985], "properties": {}, "label": "O", "xyz": [0.9036890919927429, 9.00945731699274, 11.254963245507255]}, {"species": [{"element": "O", "occu": 1}], "abc": [0.5557435808000013, 0.055743580800001406, 0.19425641919999848], "properties": {}, "label": "O", "xyz": [9.00945731699274, 0.9036890919927429, 3.149195020507255]}, {"species": [{"element": "O", "occu": 1}], "abc": [0.5557435808000013, 0.055743580800001406, 0.6942564191999985], "properties": {}, "label": "O", "xyz": [9.00945731699274, 0.9036890919927429, 11.254963245507255]}, {"species": [{"element": "O", "occu": 1}], "abc": [0.5557435808000013, 0.5557435808000013, 0.19425641919999848], "properties": {}, "label": "O", "xyz": [9.00945731699274, 9.00945731699274, 3.149195020507255]}, {"species": [{"element": "O", "occu": 1}], "abc": [0.5557435808000013, 0.5557435808000013, 0.6942564191999985], "properties": {}, "label": "O", "xyz": [9.00945731699274, 9.00945731699274, 11.254963245507255]}, {"species": [{"element": "O", "occu": 1}], "abc": [0.055743580800001406, 0.3057435808000015, 0.4442564191999985], "properties": {}, "label": "O", "xyz": [0.9036890919927429, 4.956573204492745, 7.202079133007255]}, {"species": [{"element": "O", "occu": 1}], "abc": [0.055743580800001406, 0.3057435808000015, 0.9442564191999984], "properties": {}, "label": "O", "xyz": [0.9036890919927429, 4.956573204492745, 15.307847358007255]}, {"species": [{"element": "O", "occu": 1}], "abc": [0.055743580800001406, 0.8057435808000015, 0.4442564191999985], "properties": {}, "label": "O", "xyz": [0.9036890919927429, 13.062341429492745, 7.202079133007255]}, {"species": [{"element": "O", "occu": 1}], "abc": [0.055743580800001406, 0.8057435808000015, 0.9442564191999984], "properties": {}, "label": "O", "xyz": [0.9036890919927429, 13.062341429492745, 15.307847358007255]}, {"species": [{"element": "O", "occu": 1}], "abc": [0.5557435808000013, 0.3057435808000015, 0.4442564191999985], "properties": {}, "label": "O", "xyz": [9.00945731699274, 4.956573204492745, 7.202079133007255]}, {"species": [{"element": "O", "occu": 1}], "abc": [0.5557435808000013, 0.3057435808000015, 0.9442564191999984], "properties": {}, "label": "O", "xyz": [9.00945731699274, 4.956573204492745, 15.307847358007255]}, {"species": [{"element": "O", "occu": 1}], "abc": [0.5557435808000013, 0.8057435808000015, 0.4442564191999985], "properties": {}, "label": "O", "xyz": [9.00945731699274, 13.062341429492745, 7.202079133007255]}, {"species": [{"element": "O", "occu": 1}], "abc": [0.5557435808000013, 0.8057435808000015, 0.9442564191999984], "properties": {}, "label": "O", "xyz": [9.00945731699274, 13.062341429492745, 15.307847358007255]}, {"species": [{"element": "O", "occu": 1}], "abc": [0.3057435808000015, 0.055743580800001406, 0.4442564191999985], "properties": {}, "label": "O", "xyz": [4.956573204492745, 0.9036890919927429, 7.202079133007255]}, {"species": [{"element": "O", "occu": 1}], "abc": [0.3057435808000015, 0.055743580800001406, 0.9442564191999984], "properties": {}, "label": "O", "xyz": [4.956573204492745, 0.9036890919927429, 15.307847358007255]}, {"species": [{"element": "O", "occu": 1}], "abc": [0.3057435808000015, 0.5557435808000013, 0.4442564191999985], "properties": {}, "label": "O", "xyz": [4.956573204492745, 9.00945731699274, 7.202079133007255]}, {"species": [{"element": "O", "occu": 1}], "abc": [0.3057435808000015, 0.5557435808000013, 0.9442564191999984], "properties": {}, "label": "O", "xyz": [4.956573204492745, 9.00945731699274, 15.307847358007255]}, {"species": [{"element": "O", "occu": 1}], "abc": [0.8057435808000015, 0.055743580800001406, 0.4442564191999985], "properties": {}, "label": "O", "xyz": [13.062341429492745, 0.9036890919927429, 7.202079133007255]}, {"species": [{"element": "O", "occu": 1}], "abc": [0.8057435808000015, 0.055743580800001406, 0.9442564191999984], "properties": {}, "label": "O", "xyz": [13.062341429492745, 0.9036890919927429, 15.307847358007255]}, {"species": [{"element": "O", "occu": 1}], "abc": [0.8057435808000015, 0.5557435808000013, 0.4442564191999985], "properties": {}, "label": "O", "xyz": [13.062341429492745, 9.00945731699274, 7.202079133007255]}, {"species": [{"element": "O", "occu": 1}], "abc": [0.8057435808000015, 0.5557435808000013, 0.9442564191999984], "properties": {}, "label": "O", "xyz": [13.062341429492745, 9.00945731699274, 15.307847358007255]}, {"species": [{"element": "O", "occu": 1}], "abc": [0.3057435808000015, 0.19425641919999848, 0.3057435808000015], "properties": {}, "label": "O", "xyz": [4.956573204492745, 3.149195020507255, 4.956573204492745]}, {"species": [{"element": "O", "occu": 1}], "abc": [0.3057435808000015, 0.19425641919999848, 0.8057435808000015], "properties": {}, "label": "O", "xyz": [4.956573204492745, 3.149195020507255, 13.062341429492745]}, {"species": [{"element": "O", "occu": 1}], "abc": [0.3057435808000015, 0.6942564191999985, 0.3057435808000015], "properties": {}, "label": "O", "xyz": [4.956573204492745, 11.254963245507255, 4.956573204492745]}, {"species": [{"element": "O", "occu": 1}], "abc": [0.3057435808000015, 0.6942564191999985, 0.8057435808000015], "properties": {}, "label": "O", "xyz": [4.956573204492745, 11.254963245507255, 13.062341429492745]}, {"species": [{"element": "O", "occu": 1}], "abc": [0.8057435808000015, 0.19425641919999848, 0.3057435808000015], "properties": {}, "label": "O", "xyz": [13.062341429492745, 3.149195020507255, 4.956573204492745]}, {"species": [{"element": "O", "occu": 1}], "abc": [0.8057435808000015, 0.19425641919999848, 0.8057435808000015], "properties": {}, "label": "O", "xyz": [13.062341429492745, 3.149195020507255, 13.062341429492745]}, {"species": [{"element": "O", "occu": 1}], "abc": [0.8057435808000015, 0.6942564191999985, 0.3057435808000015], "properties": {}, "label": "O", "xyz": [13.062341429492745, 11.254963245507255, 4.956573204492745]}, {"species": [{"element": "O", "occu": 1}], "abc": [0.8057435808000015, 0.6942564191999985, 0.8057435808000015], "properties": {}, "label": "O", "xyz": [13.062341429492745, 11.254963245507255, 13.062341429492745]}, {"species": [{"element": "O", "occu": 1}], "abc": [0.055743580800001406, 0.4442564191999985, 0.3057435808000015], "properties": {}, "label": "O", "xyz": [0.9036890919927429, 7.202079133007255, 4.956573204492745]}, {"species": [{"element": "O", "occu": 1}], "abc": [0.055743580800001406, 0.4442564191999985, 0.8057435808000015], "properties": {}, "label": "O", "xyz": [0.9036890919927429, 7.202079133007255, 13.062341429492745]}, {"species": [{"element": "O", "occu": 1}], "abc": [0.055743580800001406, 0.9442564191999984, 0.3057435808000015], "properties": {}, "label": "O", "xyz": [0.9036890919927429, 15.307847358007255, 4.956573204492745]}, {"species": [{"element": "O", "occu": 1}], "abc": [0.055743580800001406, 0.9442564191999984, 0.8057435808000015], "properties": {}, "label": "O", "xyz": [0.9036890919927429, 15.307847358007255, 13.062341429492745]}, {"species": [{"element": "O", "occu": 1}], "abc": [0.5557435808000013, 0.4442564191999985, 0.3057435808000015], "properties": {}, "label": "O", "xyz": [9.00945731699274, 7.202079133007255, 4.956573204492745]}, {"species": [{"element": "O", "occu": 1}], "abc": [0.5557435808000013, 0.4442564191999985, 0.8057435808000015], "properties": {}, "label": "O", "xyz": [9.00945731699274, 7.202079133007255, 13.062341429492745]}, {"species": [{"element": "O", "occu": 1}], "abc": [0.5557435808000013, 0.9442564191999984, 0.3057435808000015], "properties": {}, "label": "O", "xyz": [9.00945731699274, 15.307847358007255, 4.956573204492745]}, {"species": [{"element": "O", "occu": 1}], "abc": [0.5557435808000013, 0.9442564191999984, 0.8057435808000015], "properties": {}, "label": "O", "xyz": [9.00945731699274, 15.307847358007255, 13.062341429492745]}, {"species": [{"element": "O", "occu": 1}], "abc": [0.055743580800001406, 0.19425641919999848, 0.055743580800001406], "properties": {}, "label": "O", "xyz": [0.9036890919927429, 3.149195020507255, 0.9036890919927429]}, {"species": [{"element": "O", "occu": 1}], "abc": [0.055743580800001406, 0.19425641919999848, 0.5557435808000013], "properties": {}, "label": "O", "xyz": [0.9036890919927429, 3.149195020507255, 9.00945731699274]}, {"species": [{"element": "O", "occu": 1}], "abc": [0.055743580800001406, 0.6942564191999985, 0.055743580800001406], "properties": {}, "label": "O", "xyz": [0.9036890919927429, 11.254963245507255, 0.9036890919927429]}, {"species": [{"element": "O", "occu": 1}], "abc": [0.055743580800001406, 0.6942564191999985, 0.5557435808000013], "properties": {}, "label": "O", "xyz": [0.9036890919927429, 11.254963245507255, 9.00945731699274]}, {"species": [{"element": "O", "occu": 1}], "abc": [0.5557435808000013, 0.19425641919999848, 0.055743580800001406], "properties": {}, "label": "O", "xyz": [9.00945731699274, 3.149195020507255, 0.9036890919927429]}, {"species": [{"element": "O", "occu": 1}], "abc": [0.5557435808000013, 0.19425641919999848, 0.5557435808000013], "properties": {}, "label": "O", "xyz": [9.00945731699274, 3.149195020507255, 9.00945731699274]}, {"species": [{"element": "O", "occu": 1}], "abc": [0.5557435808000013, 0.6942564191999985, 0.055743580800001406], "properties": {}, "label": "O", "xyz": [9.00945731699274, 11.254963245507255, 0.9036890919927429]}, {"species": [{"element": "O", "occu": 1}], "abc": [0.5557435808000013, 0.6942564191999985, 0.5557435808000013], "properties": {}, "label": "O", "xyz": [9.00945731699274, 11.254963245507255, 9.00945731699274]}, {"species": [{"element": "O", "occu": 1}], "abc": [0.3057435808000015, 0.4442564191999985, 0.055743580800001406], "properties": {}, "label": "O", "xyz": [4.956573204492745, 7.202079133007255, 0.9036890919927429]}, {"species": [{"element": "O", "occu": 1}], "abc": [0.3057435808000015, 0.4442564191999985, 0.5557435808000013], "properties": {}, "label": "O", "xyz": [4.956573204492745, 7.202079133007255, 9.00945731699274]}, {"species": [{"element": "O", "occu": 1}], "abc": [0.3057435808000015, 0.9442564191999984, 0.055743580800001406], "properties": {}, "label": "O", "xyz": [4.956573204492745, 15.307847358007255, 0.9036890919927429]}, {"species": [{"element": "O", "occu": 1}], "abc": [0.3057435808000015, 0.9442564191999984, 0.5557435808000013], "properties": {}, "label": "O", "xyz": [4.956573204492745, 15.307847358007255, 9.00945731699274]}, {"species": [{"element": "O", "occu": 1}], "abc": [0.8057435808000015, 0.4442564191999985, 0.055743580800001406], "properties": {}, "label": "O", "xyz": [13.062341429492745, 7.202079133007255, 0.9036890919927429]}, {"species": [{"element": "O", "occu": 1}], "abc": [0.8057435808000015, 0.4442564191999985, 0.5557435808000013], "properties": {}, "label": "O", "xyz": [13.062341429492745, 7.202079133007255, 9.00945731699274]}, {"species": [{"element": "O", "occu": 1}], "abc": [0.8057435808000015, 0.9442564191999984, 0.055743580800001406], "properties": {}, "label": "O", "xyz": [13.062341429492745, 15.307847358007255, 0.9036890919927429]}, {"species": [{"element": "O", "occu": 1}], "abc": [0.8057435808000015, 0.9442564191999984, 0.5557435808000013], "properties": {}, "label": "O", "xyz": [13.062341429492745, 15.307847358007255, 9.00945731699274]}, {"species": [{"element": "O", "occu": 1}], "abc": [0.3192564191999984, 0.3192564191999984, 0.4307435808000014], "properties": {}, "label": "O", "xyz": [5.175637076757255, 5.175637076757255, 6.983015260742743]}, {"species": [{"element": "O", "occu": 1}], "abc": [0.3192564191999984, 0.3192564191999984, 0.9307435808000014], "properties": {}, "label": "O", "xyz": [5.175637076757255, 5.175637076757255, 15.088783485742743]}, {"species": [{"element": "O", "occu": 1}], "abc": [0.3192564191999984, 0.8192564191999984, 0.4307435808000014], "properties": {}, "label": "O", "xyz": [5.175637076757255, 13.281405301757253, 6.983015260742743]}, {"species": [{"element": "O", "occu": 1}], "abc": [0.3192564191999984, 0.8192564191999984, 0.9307435808000014], "properties": {}, "label": "O", "xyz": [5.175637076757255, 13.281405301757253, 15.088783485742743]}, {"species": [{"element": "O", "occu": 1}], "abc": [0.8192564191999984, 0.3192564191999984, 0.4307435808000014], "properties": {}, "label": "O", "xyz": [13.281405301757253, 5.175637076757255, 6.983015260742743]}, {"species": [{"element": "O", "occu": 1}], "abc": [0.8192564191999984, 0.3192564191999984, 0.9307435808000014], "properties": {}, "label": "O", "xyz": [13.281405301757253, 5.175637076757255, 15.088783485742743]}, {"species": [{"element": "O", "occu": 1}], "abc": [0.8192564191999984, 0.8192564191999984, 0.4307435808000014], "properties": {}, "label": "O", "xyz": [13.281405301757253, 13.281405301757253, 6.983015260742743]}, {"species": [{"element": "O", "occu": 1}], "abc": [0.8192564191999984, 0.8192564191999984, 0.9307435808000014], "properties": {}, "label": "O", "xyz": [13.281405301757253, 13.281405301757253, 15.088783485742743]}, {"species": [{"element": "O", "occu": 1}], "abc": [0.06925641919999836, 0.06925641919999836, 0.4307435808000014], "properties": {}, "label": "O", "xyz": [1.1227529642572533, 1.1227529642572533, 6.983015260742743]}, {"species": [{"element": "O", "occu": 1}], "abc": [0.06925641919999836, 0.06925641919999836, 0.9307435808000014], "properties": {}, "label": "O", "xyz": [1.1227529642572533, 1.1227529642572533, 15.088783485742743]}, {"species": [{"element": "O", "occu": 1}], "abc": [0.06925641919999836, 0.5692564191999984, 0.4307435808000014], "properties": {}, "label": "O", "xyz": [1.1227529642572533, 9.228521189257254, 6.983015260742743]}, {"species": [{"element": "O", "occu": 1}], "abc": [0.06925641919999836, 0.5692564191999984, 0.9307435808000014], "properties": {}, "label": "O", "xyz": [1.1227529642572533, 9.228521189257254, 15.088783485742743]}, {"species": [{"element": "O", "occu": 1}], "abc": [0.5692564191999984, 0.06925641919999836, 0.4307435808000014], "properties": {}, "label": "O", "xyz": [9.228521189257254, 1.1227529642572533, 6.983015260742743]}, {"species": [{"element": "O", "occu": 1}], "abc": [0.5692564191999984, 0.06925641919999836, 0.9307435808000014], "properties": {}, "label": "O", "xyz": [9.228521189257254, 1.1227529642572533, 15.088783485742743]}, {"species": [{"element": "O", "occu": 1}], "abc": [0.5692564191999984, 0.5692564191999984, 0.4307435808000014], "properties": {}, "label": "O", "xyz": [9.228521189257254, 9.228521189257254, 6.983015260742743]}, {"species": [{"element": "O", "occu": 1}], "abc": [0.5692564191999984, 0.5692564191999984, 0.9307435808000014], "properties": {}, "label": "O", "xyz": [9.228521189257254, 9.228521189257254, 15.088783485742743]}, {"species": [{"element": "O", "occu": 1}], "abc": [0.06925641919999836, 0.3192564191999984, 0.18074358080000152], "properties": {}, "label": "O", "xyz": [1.1227529642572533, 5.175637076757255, 2.930131148242745]}, {"species": [{"element": "O", "occu": 1}], "abc": [0.06925641919999836, 0.3192564191999984, 0.6807435808000015], "properties": {}, "label": "O", "xyz": [1.1227529642572533, 5.175637076757255, 11.035899373242746]}, {"species": [{"element": "O", "occu": 1}], "abc": [0.06925641919999836, 0.8192564191999984, 0.18074358080000152], "properties": {}, "label": "O", "xyz": [1.1227529642572533, 13.281405301757253, 2.930131148242745]}, {"species": [{"element": "O", "occu": 1}], "abc": [0.06925641919999836, 0.8192564191999984, 0.6807435808000015], "properties": {}, "label": "O", "xyz": [1.1227529642572533, 13.281405301757253, 11.035899373242746]}, {"species": [{"element": "O", "occu": 1}], "abc": [0.5692564191999984, 0.3192564191999984, 0.18074358080000152], "properties": {}, "label": "O", "xyz": [9.228521189257254, 5.175637076757255, 2.930131148242745]}, {"species": [{"element": "O", "occu": 1}], "abc": [0.5692564191999984, 0.3192564191999984, 0.6807435808000015], "properties": {}, "label": "O", "xyz": [9.228521189257254, 5.175637076757255, 11.035899373242746]}, {"species": [{"element": "O", "occu": 1}], "abc": [0.5692564191999984, 0.8192564191999984, 0.18074358080000152], "properties": {}, "label": "O", "xyz": [9.228521189257254, 13.281405301757253, 2.930131148242745]}, {"species": [{"element": "O", "occu": 1}], "abc": [0.5692564191999984, 0.8192564191999984, 0.6807435808000015], "properties": {}, "label": "O", "xyz": [9.228521189257254, 13.281405301757253, 11.035899373242746]}, {"species": [{"element": "O", "occu": 1}], "abc": [0.3192564191999984, 0.06925641919999836, 0.18074358080000152], "properties": {}, "label": "O", "xyz": [5.175637076757255, 1.1227529642572533, 2.930131148242745]}, {"species": [{"element": "O", "occu": 1}], "abc": [0.3192564191999984, 0.06925641919999836, 0.6807435808000015], "properties": {}, "label": "O", "xyz": [5.175637076757255, 1.1227529642572533, 11.035899373242746]}, {"species": [{"element": "O", "occu": 1}], "abc": [0.3192564191999984, 0.5692564191999984, 0.18074358080000152], "properties": {}, "label": "O", "xyz": [5.175637076757255, 9.228521189257254, 2.930131148242745]}, {"species": [{"element": "O", "occu": 1}], "abc": [0.3192564191999984, 0.5692564191999984, 0.6807435808000015], "properties": {}, "label": "O", "xyz": [5.175637076757255, 9.228521189257254, 11.035899373242746]}, {"species": [{"element": "O", "occu": 1}], "abc": [0.8192564191999984, 0.06925641919999836, 0.18074358080000152], "properties": {}, "label": "O", "xyz": [13.281405301757253, 1.1227529642572533, 2.930131148242745]}, {"species": [{"element": "O", "occu": 1}], "abc": [0.8192564191999984, 0.06925641919999836, 0.6807435808000015], "properties": {}, "label": "O", "xyz": [13.281405301757253, 1.1227529642572533, 11.035899373242746]}, {"species": [{"element": "O", "occu": 1}], "abc": [0.8192564191999984, 0.5692564191999984, 0.18074358080000152], "properties": {}, "label": "O", "xyz": [13.281405301757253, 9.228521189257254, 2.930131148242745]}, {"species": [{"element": "O", "occu": 1}], "abc": [0.8192564191999984, 0.5692564191999984, 0.6807435808000015], "properties": {}, "label": "O", "xyz": [13.281405301757253, 9.228521189257254, 11.035899373242746]}, {"species": [{"element": "O", "occu": 1}], "abc": [0.3192564191999984, 0.4307435808000014, 0.3192564191999984], "properties": {}, "label": "O", "xyz": [5.175637076757255, 6.983015260742743, 5.175637076757255]}, {"species": [{"element": "O", "occu": 1}], "abc": [0.3192564191999984, 0.4307435808000014, 0.8192564191999984], "properties": {}, "label": "O", "xyz": [5.175637076757255, 6.983015260742743, 13.281405301757253]}, {"species": [{"element": "O", "occu": 1}], "abc": [0.3192564191999984, 0.9307435808000014, 0.3192564191999984], "properties": {}, "label": "O", "xyz": [5.175637076757255, 15.088783485742743, 5.175637076757255]}, {"species": [{"element": "O", "occu": 1}], "abc": [0.3192564191999984, 0.9307435808000014, 0.8192564191999984], "properties": {}, "label": "O", "xyz": [5.175637076757255, 15.088783485742743, 13.281405301757253]}, {"species": [{"element": "O", "occu": 1}], "abc": [0.8192564191999984, 0.4307435808000014, 0.3192564191999984], "properties": {}, "label": "O", "xyz": [13.281405301757253, 6.983015260742743, 5.175637076757255]}, {"species": [{"element": "O", "occu": 1}], "abc": [0.8192564191999984, 0.4307435808000014, 0.8192564191999984], "properties": {}, "label": "O", "xyz": [13.281405301757253, 6.983015260742743, 13.281405301757253]}, {"species": [{"element": "O", "occu": 1}], "abc": [0.8192564191999984, 0.9307435808000014, 0.3192564191999984], "properties": {}, "label": "O", "xyz": [13.281405301757253, 15.088783485742743, 5.175637076757255]}, {"species": [{"element": "O", "occu": 1}], "abc": [0.8192564191999984, 0.9307435808000014, 0.8192564191999984], "properties": {}, "label": "O", "xyz": [13.281405301757253, 15.088783485742743, 13.281405301757253]}, {"species": [{"element": "O", "occu": 1}], "abc": [0.06925641919999836, 0.18074358080000152, 0.3192564191999984], "properties": {}, "label": "O", "xyz": [1.1227529642572533, 2.930131148242745, 5.175637076757255]}, {"species": [{"element": "O", "occu": 1}], "abc": [0.06925641919999836, 0.18074358080000152, 0.8192564191999984], "properties": {}, "label": "O", "xyz": [1.1227529642572533, 2.930131148242745, 13.281405301757253]}, {"species": [{"element": "O", "occu": 1}], "abc": [0.06925641919999836, 0.6807435808000015, 0.3192564191999984], "properties": {}, "label": "O", "xyz": [1.1227529642572533, 11.035899373242746, 5.175637076757255]}, {"species": [{"element": "O", "occu": 1}], "abc": [0.06925641919999836, 0.6807435808000015, 0.8192564191999984], "properties": {}, "label": "O", "xyz": [1.1227529642572533, 11.035899373242746, 13.281405301757253]}, {"species": [{"element": "O", "occu": 1}], "abc": [0.5692564191999984, 0.18074358080000152, 0.3192564191999984], "properties": {}, "label": "O", "xyz": [9.228521189257254, 2.930131148242745, 5.175637076757255]}, {"species": [{"element": "O", "occu": 1}], "abc": [0.5692564191999984, 0.18074358080000152, 0.8192564191999984], "properties": {}, "label": "O", "xyz": [9.228521189257254, 2.930131148242745, 13.281405301757253]}, {"species": [{"element": "O", "occu": 1}], "abc": [0.5692564191999984, 0.6807435808000015, 0.3192564191999984], "properties": {}, "label": "O", "xyz": [9.228521189257254, 11.035899373242746, 5.175637076757255]}, {"species": [{"element": "O", "occu": 1}], "abc": [0.5692564191999984, 0.6807435808000015, 0.8192564191999984], "properties": {}, "label": "O", "xyz": [9.228521189257254, 11.035899373242746, 13.281405301757253]}, {"species": [{"element": "O", "occu": 1}], "abc": [0.06925641919999836, 0.4307435808000014, 0.06925641919999836], "properties": {}, "label": "O", "xyz": [1.1227529642572533, 6.983015260742743, 1.1227529642572533]}, {"species": [{"element": "O", "occu": 1}], "abc": [0.06925641919999836, 0.4307435808000014, 0.5692564191999984], "properties": {}, "label": "O", "xyz": [1.1227529642572533, 6.983015260742743, 9.228521189257254]}, {"species": [{"element": "O", "occu": 1}], "abc": [0.06925641919999836, 0.9307435808000014, 0.06925641919999836], "properties": {}, "label": "O", "xyz": [1.1227529642572533, 15.088783485742743, 1.1227529642572533]}, {"species": [{"element": "O", "occu": 1}], "abc": [0.06925641919999836, 0.9307435808000014, 0.5692564191999984], "properties": {}, "label": "O", "xyz": [1.1227529642572533, 15.088783485742743, 9.228521189257254]}, {"species": [{"element": "O", "occu": 1}], "abc": [0.5692564191999984, 0.4307435808000014, 0.06925641919999836], "properties": {}, "label": "O", "xyz": [9.228521189257254, 6.983015260742743, 1.1227529642572533]}, {"species": [{"element": "O", "occu": 1}], "abc": [0.5692564191999984, 0.4307435808000014, 0.5692564191999984], "properties": {}, "label": "O", "xyz": [9.228521189257254, 6.983015260742743, 9.228521189257254]}, {"species": [{"element": "O", "occu": 1}], "abc": [0.5692564191999984, 0.9307435808000014, 0.06925641919999836], "properties": {}, "label": "O", "xyz": [9.228521189257254, 15.088783485742743, 1.1227529642572533]}, {"species": [{"element": "O", "occu": 1}], "abc": [0.5692564191999984, 0.9307435808000014, 0.5692564191999984], "properties": {}, "label": "O", "xyz": [9.228521189257254, 15.088783485742743, 9.228521189257254]}, {"species": [{"element": "O", "occu": 1}], "abc": [0.3192564191999984, 0.18074358080000152, 0.06925641919999836], "properties": {}, "label": "O", "xyz": [5.175637076757255, 2.930131148242745, 1.1227529642572533]}, {"species": [{"element": "O", "occu": 1}], "abc": [0.3192564191999984, 0.18074358080000152, 0.5692564191999984], "properties": {}, "label": "O", "xyz": [5.175637076757255, 2.930131148242745, 9.228521189257254]}, {"species": [{"element": "O", "occu": 1}], "abc": [0.3192564191999984, 0.6807435808000015, 0.06925641919999836], "properties": {}, "label": "O", "xyz": [5.175637076757255, 11.035899373242746, 1.1227529642572533]}, {"species": [{"element": "O", "occu": 1}], "abc": [0.3192564191999984, 0.6807435808000015, 0.5692564191999984], "properties": {}, "label": "O", "xyz": [5.175637076757255, 11.035899373242746, 9.228521189257254]}, {"species": [{"element": "O", "occu": 1}], "abc": [0.8192564191999984, 0.18074358080000152, 0.06925641919999836], "properties": {}, "label": "O", "xyz": [13.281405301757253, 2.930131148242745, 1.1227529642572533]}, {"species": [{"element": "O", "occu": 1}], "abc": [0.8192564191999984, 0.18074358080000152, 0.5692564191999984], "properties": {}, "label": "O", "xyz": [13.281405301757253, 2.930131148242745, 9.228521189257254]}, {"species": [{"element": "O", "occu": 1}], "abc": [0.8192564191999984, 0.6807435808000015, 0.06925641919999836], "properties": {}, "label": "O", "xyz": [13.281405301757253, 11.035899373242746, 1.1227529642572533]}, {"species": [{"element": "O", "occu": 1}], "abc": [0.8192564191999984, 0.6807435808000015, 0.5692564191999984], "properties": {}, "label": "O", "xyz": [13.281405301757253, 11.035899373242746, 9.228521189257254]}, {"species": [{"element": "O", "occu": 1}], "abc": [0.19425641919999848, 0.19425641919999848, 0.19425641919999848], "properties": {}, "label": "O", "xyz": [3.149195020507255, 3.149195020507255, 3.149195020507255]}, {"species": [{"element": "O", "occu": 1}], "abc": [0.19425641919999848, 0.19425641919999848, 0.6942564191999985], "properties": {}, "label": "O", "xyz": [3.149195020507255, 3.149195020507255, 11.254963245507255]}, {"species": [{"element": "O", "occu": 1}], "abc": [0.19425641919999848, 0.6942564191999985, 0.19425641919999848], "properties": {}, "label": "O", "xyz": [3.149195020507255, 11.254963245507255, 3.149195020507255]}, {"species": [{"element": "O", "occu": 1}], "abc": [0.19425641919999848, 0.6942564191999985, 0.6942564191999985], "properties": {}, "label": "O", "xyz": [3.149195020507255, 11.254963245507255, 11.254963245507255]}, {"species": [{"element": "O", "occu": 1}], "abc": [0.6942564191999985, 0.19425641919999848, 0.19425641919999848], "properties": {}, "label": "O", "xyz": [11.254963245507255, 3.149195020507255, 3.149195020507255]}, {"species": [{"element": "O", "occu": 1}], "abc": [0.6942564191999985, 0.19425641919999848, 0.6942564191999985], "properties": {}, "label": "O", "xyz": [11.254963245507255, 3.149195020507255, 11.254963245507255]}, {"species": [{"element": "O", "occu": 1}], "abc": [0.6942564191999985, 0.6942564191999985, 0.19425641919999848], "properties": {}, "label": "O", "xyz": [11.254963245507255, 11.254963245507255, 3.149195020507255]}, {"species": [{"element": "O", "occu": 1}], "abc": [0.6942564191999985, 0.6942564191999985, 0.6942564191999985], "properties": {}, "label": "O", "xyz": [11.254963245507255, 11.254963245507255, 11.254963245507255]}, {"species": [{"element": "O", "occu": 1}], "abc": [0.4442564191999985, 0.4442564191999985, 0.19425641919999848], "properties": {}, "label": "O", "xyz": [7.202079133007255, 7.202079133007255, 3.149195020507255]}, {"species": [{"element": "O", "occu": 1}], "abc": [0.4442564191999985, 0.4442564191999985, 0.6942564191999985], "properties": {}, "label": "O", "xyz": [7.202079133007255, 7.202079133007255, 11.254963245507255]}, {"species": [{"element": "O", "occu": 1}], "abc": [0.4442564191999985, 0.9442564191999984, 0.19425641919999848], "properties": {}, "label": "O", "xyz": [7.202079133007255, 15.307847358007255, 3.149195020507255]}, {"species": [{"element": "O", "occu": 1}], "abc": [0.4442564191999985, 0.9442564191999984, 0.6942564191999985], "properties": {}, "label": "O", "xyz": [7.202079133007255, 15.307847358007255, 11.254963245507255]}, {"species": [{"element": "O", "occu": 1}], "abc": [0.9442564191999984, 0.4442564191999985, 0.19425641919999848], "properties": {}, "label": "O", "xyz": [15.307847358007255, 7.202079133007255, 3.149195020507255]}, {"species": [{"element": "O", "occu": 1}], "abc": [0.9442564191999984, 0.4442564191999985, 0.6942564191999985], "properties": {}, "label": "O", "xyz": [15.307847358007255, 7.202079133007255, 11.254963245507255]}, {"species": [{"element": "O", "occu": 1}], "abc": [0.9442564191999984, 0.9442564191999984, 0.19425641919999848], "properties": {}, "label": "O", "xyz": [15.307847358007255, 15.307847358007255, 3.149195020507255]}, {"species": [{"element": "O", "occu": 1}], "abc": [0.9442564191999984, 0.9442564191999984, 0.6942564191999985], "properties": {}, "label": "O", "xyz": [15.307847358007255, 15.307847358007255, 11.254963245507255]}, {"species": [{"element": "O", "occu": 1}], "abc": [0.4442564191999985, 0.19425641919999848, 0.4442564191999985], "properties": {}, "label": "O", "xyz": [7.202079133007255, 3.149195020507255, 7.202079133007255]}, {"species": [{"element": "O", "occu": 1}], "abc": [0.4442564191999985, 0.19425641919999848, 0.9442564191999984], "properties": {}, "label": "O", "xyz": [7.202079133007255, 3.149195020507255, 15.307847358007255]}, {"species": [{"element": "O", "occu": 1}], "abc": [0.4442564191999985, 0.6942564191999985, 0.4442564191999985], "properties": {}, "label": "O", "xyz": [7.202079133007255, 11.254963245507255, 7.202079133007255]}, {"species": [{"element": "O", "occu": 1}], "abc": [0.4442564191999985, 0.6942564191999985, 0.9442564191999984], "properties": {}, "label": "O", "xyz": [7.202079133007255, 11.254963245507255, 15.307847358007255]}, {"species": [{"element": "O", "occu": 1}], "abc": [0.9442564191999984, 0.19425641919999848, 0.4442564191999985], "properties": {}, "label": "O", "xyz": [15.307847358007255, 3.149195020507255, 7.202079133007255]}, {"species": [{"element": "O", "occu": 1}], "abc": [0.9442564191999984, 0.19425641919999848, 0.9442564191999984], "properties": {}, "label": "O", "xyz": [15.307847358007255, 3.149195020507255, 15.307847358007255]}, {"species": [{"element": "O", "occu": 1}], "abc": [0.9442564191999984, 0.6942564191999985, 0.4442564191999985], "properties": {}, "label": "O", "xyz": [15.307847358007255, 11.254963245507255, 7.202079133007255]}, {"species": [{"element": "O", "occu": 1}], "abc": [0.9442564191999984, 0.6942564191999985, 0.9442564191999984], "properties": {}, "label": "O", "xyz": [15.307847358007255, 11.254963245507255, 15.307847358007255]}, {"species": [{"element": "O", "occu": 1}], "abc": [0.19425641919999848, 0.4442564191999985, 0.4442564191999985], "properties": {}, "label": "O", "xyz": [3.149195020507255, 7.202079133007255, 7.202079133007255]}, {"species": [{"element": "O", "occu": 1}], "abc": [0.19425641919999848, 0.4442564191999985, 0.9442564191999984], "properties": {}, "label": "O", "xyz": [3.149195020507255, 7.202079133007255, 15.307847358007255]}, {"species": [{"element": "O", "occu": 1}], "abc": [0.19425641919999848, 0.9442564191999984, 0.4442564191999985], "properties": {}, "label": "O", "xyz": [3.149195020507255, 15.307847358007255, 7.202079133007255]}, {"species": [{"element": "O", "occu": 1}], "abc": [0.19425641919999848, 0.9442564191999984, 0.9442564191999984], "properties": {}, "label": "O", "xyz": [3.149195020507255, 15.307847358007255, 15.307847358007255]}, {"species": [{"element": "O", "occu": 1}], "abc": [0.6942564191999985, 0.4442564191999985, 0.4442564191999985], "properties": {}, "label": "O", "xyz": [11.254963245507255, 7.202079133007255, 7.202079133007255]}, {"species": [{"element": "O", "occu": 1}], "abc": [0.6942564191999985, 0.4442564191999985, 0.9442564191999984], "properties": {}, "label": "O", "xyz": [11.254963245507255, 7.202079133007255, 15.307847358007255]}, {"species": [{"element": "O", "occu": 1}], "abc": [0.6942564191999985, 0.9442564191999984, 0.4442564191999985], "properties": {}, "label": "O", "xyz": [11.254963245507255, 15.307847358007255, 7.202079133007255]}, {"species": [{"element": "O", "occu": 1}], "abc": [0.6942564191999985, 0.9442564191999984, 0.9442564191999984], "properties": {}, "label": "O", "xyz": [11.254963245507255, 15.307847358007255, 15.307847358007255]}, {"species": [{"element": "O", "occu": 1}], "abc": [0.4307435808000014, 0.3192564191999984, 0.3192564191999984], "properties": {}, "label": "O", "xyz": [6.983015260742743, 5.175637076757255, 5.175637076757255]}, {"species": [{"element": "O", "occu": 1}], "abc": [0.4307435808000014, 0.3192564191999984, 0.8192564191999984], "properties": {}, "label": "O", "xyz": [6.983015260742743, 5.175637076757255, 13.281405301757253]}, {"species": [{"element": "O", "occu": 1}], "abc": [0.4307435808000014, 0.8192564191999984, 0.3192564191999984], "properties": {}, "label": "O", "xyz": [6.983015260742743, 13.281405301757253, 5.175637076757255]}, {"species": [{"element": "O", "occu": 1}], "abc": [0.4307435808000014, 0.8192564191999984, 0.8192564191999984], "properties": {}, "label": "O", "xyz": [6.983015260742743, 13.281405301757253, 13.281405301757253]}, {"species": [{"element": "O", "occu": 1}], "abc": [0.9307435808000014, 0.3192564191999984, 0.3192564191999984], "properties": {}, "label": "O", "xyz": [15.088783485742743, 5.175637076757255, 5.175637076757255]}, {"species": [{"element": "O", "occu": 1}], "abc": [0.9307435808000014, 0.3192564191999984, 0.8192564191999984], "properties": {}, "label": "O", "xyz": [15.088783485742743, 5.175637076757255, 13.281405301757253]}, {"species": [{"element": "O", "occu": 1}], "abc": [0.9307435808000014, 0.8192564191999984, 0.3192564191999984], "properties": {}, "label": "O", "xyz": [15.088783485742743, 13.281405301757253, 5.175637076757255]}, {"species": [{"element": "O", "occu": 1}], "abc": [0.9307435808000014, 0.8192564191999984, 0.8192564191999984], "properties": {}, "label": "O", "xyz": [15.088783485742743, 13.281405301757253, 13.281405301757253]}, {"species": [{"element": "O", "occu": 1}], "abc": [0.18074358080000152, 0.06925641919999836, 0.3192564191999984], "properties": {}, "label": "O", "xyz": [2.930131148242745, 1.1227529642572533, 5.175637076757255]}, {"species": [{"element": "O", "occu": 1}], "abc": [0.18074358080000152, 0.06925641919999836, 0.8192564191999984], "properties": {}, "label": "O", "xyz": [2.930131148242745, 1.1227529642572533, 13.281405301757253]}, {"species": [{"element": "O", "occu": 1}], "abc": [0.18074358080000152, 0.5692564191999984, 0.3192564191999984], "properties": {}, "label": "O", "xyz": [2.930131148242745, 9.228521189257254, 5.175637076757255]}, {"species": [{"element": "O", "occu": 1}], "abc": [0.18074358080000152, 0.5692564191999984, 0.8192564191999984], "properties": {}, "label": "O", "xyz": [2.930131148242745, 9.228521189257254, 13.281405301757253]}, {"species": [{"element": "O", "occu": 1}], "abc": [0.6807435808000015, 0.06925641919999836, 0.3192564191999984], "properties": {}, "label": "O", "xyz": [11.035899373242746, 1.1227529642572533, 5.175637076757255]}, {"species": [{"element": "O", "occu": 1}], "abc": [0.6807435808000015, 0.06925641919999836, 0.8192564191999984], "properties": {}, "label": "O", "xyz": [11.035899373242746, 1.1227529642572533, 13.281405301757253]}, {"species": [{"element": "O", "occu": 1}], "abc": [0.6807435808000015, 0.5692564191999984, 0.3192564191999984], "properties": {}, "label": "O", "xyz": [11.035899373242746, 9.228521189257254, 5.175637076757255]}, {"species": [{"element": "O", "occu": 1}], "abc": [0.6807435808000015, 0.5692564191999984, 0.8192564191999984], "properties": {}, "label": "O", "xyz": [11.035899373242746, 9.228521189257254, 13.281405301757253]}, {"species": [{"element": "O", "occu": 1}], "abc": [0.18074358080000152, 0.3192564191999984, 0.06925641919999836], "properties": {}, "label": "O", "xyz": [2.930131148242745, 5.175637076757255, 1.1227529642572533]}, {"species": [{"element": "O", "occu": 1}], "abc": [0.18074358080000152, 0.3192564191999984, 0.5692564191999984], "properties": {}, "label": "O", "xyz": [2.930131148242745, 5.175637076757255, 9.228521189257254]}, {"species": [{"element": "O", "occu": 1}], "abc": [0.18074358080000152, 0.8192564191999984, 0.06925641919999836], "properties": {}, "label": "O", "xyz": [2.930131148242745, 13.281405301757253, 1.1227529642572533]}, {"species": [{"element": "O", "occu": 1}], "abc": [0.18074358080000152, 0.8192564191999984, 0.5692564191999984], "properties": {}, "label": "O", "xyz": [2.930131148242745, 13.281405301757253, 9.228521189257254]}, {"species": [{"element": "O", "occu": 1}], "abc": [0.6807435808000015, 0.3192564191999984, 0.06925641919999836], "properties": {}, "label": "O", "xyz": [11.035899373242746, 5.175637076757255, 1.1227529642572533]}, {"species": [{"element": "O", "occu": 1}], "abc": [0.6807435808000015, 0.3192564191999984, 0.5692564191999984], "properties": {}, "label": "O", "xyz": [11.035899373242746, 5.175637076757255, 9.228521189257254]}, {"species": [{"element": "O", "occu": 1}], "abc": [0.6807435808000015, 0.8192564191999984, 0.06925641919999836], "properties": {}, "label": "O", "xyz": [11.035899373242746, 13.281405301757253, 1.1227529642572533]}, {"species": [{"element": "O", "occu": 1}], "abc": [0.6807435808000015, 0.8192564191999984, 0.5692564191999984], "properties": {}, "label": "O", "xyz": [11.035899373242746, 13.281405301757253, 9.228521189257254]}, {"species": [{"element": "O", "occu": 1}], "abc": [0.4307435808000014, 0.06925641919999836, 0.06925641919999836], "properties": {}, "label": "O", "xyz": [6.983015260742743, 1.1227529642572533, 1.1227529642572533]}, {"species": [{"element": "O", "occu": 1}], "abc": [0.4307435808000014, 0.06925641919999836, 0.5692564191999984], "properties": {}, "label": "O", "xyz": [6.983015260742743, 1.1227529642572533, 9.228521189257254]}, {"species": [{"element": "O", "occu": 1}], "abc": [0.4307435808000014, 0.5692564191999984, 0.06925641919999836], "properties": {}, "label": "O", "xyz": [6.983015260742743, 9.228521189257254, 1.1227529642572533]}, {"species": [{"element": "O", "occu": 1}], "abc": [0.4307435808000014, 0.5692564191999984, 0.5692564191999984], "properties": {}, "label": "O", "xyz": [6.983015260742743, 9.228521189257254, 9.228521189257254]}, {"species": [{"element": "O", "occu": 1}], "abc": [0.9307435808000014, 0.06925641919999836, 0.06925641919999836], "properties": {}, "label": "O", "xyz": [15.088783485742743, 1.1227529642572533, 1.1227529642572533]}, {"species": [{"element": "O", "occu": 1}], "abc": [0.9307435808000014, 0.06925641919999836, 0.5692564191999984], "properties": {}, "label": "O", "xyz": [15.088783485742743, 1.1227529642572533, 9.228521189257254]}, {"species": [{"element": "O", "occu": 1}], "abc": [0.9307435808000014, 0.5692564191999984, 0.06925641919999836], "properties": {}, "label": "O", "xyz": [15.088783485742743, 9.228521189257254, 1.1227529642572533]}, {"species": [{"element": "O", "occu": 1}], "abc": [0.9307435808000014, 0.5692564191999984, 0.5692564191999984], "properties": {}, "label": "O", "xyz": [15.088783485742743, 9.228521189257254, 9.228521189257254]}]}, "site_symmetry": "1", "defect_center": [0.0, 0.0, 0.0], "perturbed_structure": null, "perturbed_sites": [], "perturbed_site_symmetry": "1"}